{
  "a_comp_cor_00": {
    "CumulativeVarianceExplained": 0.0114198212,
    "Mask": "combined",
    "Method": "aCompCor",
    "Retained": true,
    "SingularValue": 254.8848099055,
    "VarianceExplained": 0.0114198212
  },
  "a_comp_cor_01": {
    "CumulativeVarianceExplained": 0.0178313364,
    "Mask": "combined",
    "Method": "aCompCor",
    "Retained": true,
    "SingularValue": 190.982968958,
    "VarianceExplained": 0.0064115152
  },
  "a_comp_cor_02": {
    "CumulativeVarianceExplained": 0.0239631312,
    "Mask": "combined",
    "Method": "aCompCor",
    "Retained": true,
    "SingularValue": 186.7704266406,
    "VarianceExplained": 0.0061317949
  },
  "a_comp_cor_03": {
    "CumulativeVarianceExplained": 0.029812383,
    "Mask": "combined",
    "Method": "aCompCor",
    "Retained": true,
    "SingularValue": 182.4166436059,
    "VarianceExplained": 0.0058492518
  },
  "a_comp_cor_04": {
    "CumulativeVarianceExplained": 0.0354760845,
    "Mask": "combined",
    "Method": "aCompCor",
    "Retained": true,
    "SingularValue": 179.5000115366,
    "VarianceExplained": 0.0056637015
  },
  "a_comp_cor_05": {
    "CumulativeVarianceExplained": 0.0404487948,
    "Mask": "combined",
    "Method": "aCompCor",
    "Retained": true,
    "SingularValue": 168.1941484217,
    "VarianceExplained": 0.0049727103
  },
  "a_comp_cor_06": {
    "CumulativeVarianceExplained": 0.0446635565,
    "Mask": "combined",
    "Method": "aCompCor",
    "Retained": true,
    "SingularValue": 154.8462939673,
    "VarianceExplained": 0.0042147617
  },
  "a_comp_cor_07": {
    "CumulativeVarianceExplained": 0.0486742388,
    "Mask": "combined",
    "Method": "aCompCor",
    "Retained": true,
    "SingularValue": 151.0509405898,
    "VarianceExplained": 0.0040106823
  },
  "a_comp_cor_08": {
    "CumulativeVarianceExplained": 0.0524956301,
    "Mask": "combined",
    "Method": "aCompCor",
    "Retained": true,
    "SingularValue": 147.4433039799,
    "VarianceExplained": 0.0038213912
  },
  "a_comp_cor_09": {
    "CumulativeVarianceExplained": 0.0560727903,
    "Mask": "combined",
    "Method": "aCompCor",
    "Retained": true,
    "SingularValue": 142.6538509496,
    "VarianceExplained": 0.0035771602
  },
  "a_comp_cor_10": {
    "CumulativeVarianceExplained": 0.0594833194,
    "Mask": "combined",
    "Method": "aCompCor",
    "Retained": true,
    "SingularValue": 139.2916809417,
    "VarianceExplained": 0.0034105291
  },
  "a_comp_cor_100": {
    "CumulativeVarianceExplained": 0.2997358324,
    "Mask": "combined",
    "Method": "aCompCor",
    "Retained": true,
    "SingularValue": 117.5334296964,
    "VarianceExplained": 0.0024282546
  },
  "a_comp_cor_101": {
    "CumulativeVarianceExplained": 0.3021604159,
    "Mask": "combined",
    "Method": "aCompCor",
    "Retained": true,
    "SingularValue": 117.4445523803,
    "VarianceExplained": 0.0024245835
  },
  "a_comp_cor_102": {
    "CumulativeVarianceExplained": 0.3045770647,
    "Mask": "combined",
    "Method": "aCompCor",
    "Retained": true,
    "SingularValue": 117.2522203024,
    "VarianceExplained": 0.0024166488
  },
  "a_comp_cor_103": {
    "CumulativeVarianceExplained": 0.3069889219,
    "Mask": "combined",
    "Method": "aCompCor",
    "Retained": true,
    "SingularValue": 117.1359191138,
    "VarianceExplained": 0.0024118571
  },
  "a_comp_cor_104": {
    "CumulativeVarianceExplained": 0.3093988143,
    "Mask": "combined",
    "Method": "aCompCor",
    "Retained": true,
    "SingularValue": 117.088201526,
    "VarianceExplained": 0.0024098925
  },
  "a_comp_cor_105": {
    "CumulativeVarianceExplained": 0.3118067133,
    "Mask": "combined",
    "Method": "aCompCor",
    "Retained": true,
    "SingularValue": 117.0397633873,
    "VarianceExplained": 0.002407899
  },
  "a_comp_cor_106": {
    "CumulativeVarianceExplained": 0.3142077551,
    "Mask": "combined",
    "Method": "aCompCor",
    "Retained": true,
    "SingularValue": 116.8729905445,
    "VarianceExplained": 0.0024010417
  },
  "a_comp_cor_107": {
    "CumulativeVarianceExplained": 0.3166057281,
    "Mask": "combined",
    "Method": "aCompCor",
    "Retained": true,
    "SingularValue": 116.7982816499,
    "VarianceExplained": 0.0023979731
  },
  "a_comp_cor_108": {
    "CumulativeVarianceExplained": 0.3189979642,
    "Mask": "combined",
    "Method": "aCompCor",
    "Retained": true,
    "SingularValue": 116.6584815486,
    "VarianceExplained": 0.0023922361
  },
  "a_comp_cor_109": {
    "CumulativeVarianceExplained": 0.3213887803,
    "Mask": "combined",
    "Method": "aCompCor",
    "Retained": true,
    "SingularValue": 116.6238528352,
    "VarianceExplained": 0.0023908161
  },
  "a_comp_cor_11": {
    "CumulativeVarianceExplained": 0.0628665536,
    "Mask": "combined",
    "Method": "aCompCor",
    "Retained": true,
    "SingularValue": 138.7331793793,
    "VarianceExplained": 0.0033832343
  },
  "a_comp_cor_110": {
    "CumulativeVarianceExplained": 0.3237745712,
    "Mask": "combined",
    "Method": "aCompCor",
    "Retained": true,
    "SingularValue": 116.5012248101,
    "VarianceExplained": 0.0023857909
  },
  "a_comp_cor_111": {
    "CumulativeVarianceExplained": 0.3261573476,
    "Mask": "combined",
    "Method": "aCompCor",
    "Retained": true,
    "SingularValue": 116.4276025721,
    "VarianceExplained": 0.0023827765
  },
  "a_comp_cor_112": {
    "CumulativeVarianceExplained": 0.3285331295,
    "Mask": "combined",
    "Method": "aCompCor",
    "Retained": true,
    "SingularValue": 116.2565903106,
    "VarianceExplained": 0.0023757818
  },
  "a_comp_cor_113": {
    "CumulativeVarianceExplained": 0.3309053965,
    "Mask": "combined",
    "Method": "aCompCor",
    "Retained": true,
    "SingularValue": 116.170562334,
    "VarianceExplained": 0.0023722671
  },
  "a_comp_cor_114": {
    "CumulativeVarianceExplained": 0.3332757226,
    "Mask": "combined",
    "Method": "aCompCor",
    "Retained": true,
    "SingularValue": 116.1230275519,
    "VarianceExplained": 0.0023703261
  },
  "a_comp_cor_115": {
    "CumulativeVarianceExplained": 0.3356419763,
    "Mask": "combined",
    "Method": "aCompCor",
    "Retained": true,
    "SingularValue": 116.0232310105,
    "VarianceExplained": 0.0023662537
  },
  "a_comp_cor_116": {
    "CumulativeVarianceExplained": 0.3380056937,
    "Mask": "combined",
    "Method": "aCompCor",
    "Retained": true,
    "SingularValue": 115.9610337848,
    "VarianceExplained": 0.0023637174
  },
  "a_comp_cor_117": {
    "CumulativeVarianceExplained": 0.3403649525,
    "Mask": "combined",
    "Method": "aCompCor",
    "Retained": true,
    "SingularValue": 115.8516156323,
    "VarianceExplained": 0.0023592588
  },
  "a_comp_cor_118": {
    "CumulativeVarianceExplained": 0.342720678,
    "Mask": "combined",
    "Method": "aCompCor",
    "Retained": true,
    "SingularValue": 115.7648307368,
    "VarianceExplained": 0.0023557255
  },
  "a_comp_cor_119": {
    "CumulativeVarianceExplained": 0.3450674845,
    "Mask": "combined",
    "Method": "aCompCor",
    "Retained": true,
    "SingularValue": 115.5454758653,
    "VarianceExplained": 0.0023468065
  },
  "a_comp_cor_12": {
    "CumulativeVarianceExplained": 0.0661189178,
    "Mask": "combined",
    "Method": "aCompCor",
    "Retained": true,
    "SingularValue": 136.0234806347,
    "VarianceExplained": 0.0032523641
  },
  "a_comp_cor_120": {
    "CumulativeVarianceExplained": 0.3474115985,
    "Mask": "combined",
    "Method": "aCompCor",
    "Retained": true,
    "SingularValue": 115.4791733305,
    "VarianceExplained": 0.002344114
  },
  "a_comp_cor_121": {
    "CumulativeVarianceExplained": 0.3497541073,
    "Mask": "combined",
    "Method": "aCompCor",
    "Retained": true,
    "SingularValue": 115.4396284662,
    "VarianceExplained": 0.0023425088
  },
  "a_comp_cor_122": {
    "CumulativeVarianceExplained": 0.3520948081,
    "Mask": "combined",
    "Method": "aCompCor",
    "Retained": true,
    "SingularValue": 115.3950706836,
    "VarianceExplained": 0.0023407008
  },
  "a_comp_cor_123": {
    "CumulativeVarianceExplained": 0.3544303055,
    "Mask": "combined",
    "Method": "aCompCor",
    "Retained": true,
    "SingularValue": 115.266735054,
    "VarianceExplained": 0.0023354973
  },
  "a_comp_cor_124": {
    "CumulativeVarianceExplained": 0.3567614699,
    "Mask": "combined",
    "Method": "aCompCor",
    "Retained": true,
    "SingularValue": 115.1597611808,
    "VarianceExplained": 0.0023311644
  },
  "a_comp_cor_125": {
    "CumulativeVarianceExplained": 0.3590883421,
    "Mask": "combined",
    "Method": "aCompCor",
    "Retained": true,
    "SingularValue": 115.0536934137,
    "VarianceExplained": 0.0023268722
  },
  "a_comp_cor_126": {
    "CumulativeVarianceExplained": 0.3614130311,
    "Mask": "combined",
    "Method": "aCompCor",
    "Retained": true,
    "SingularValue": 114.9997084219,
    "VarianceExplained": 0.0023246891
  },
  "a_comp_cor_127": {
    "CumulativeVarianceExplained": 0.3637350043,
    "Mask": "combined",
    "Method": "aCompCor",
    "Retained": true,
    "SingularValue": 114.9325111076,
    "VarianceExplained": 0.0023219731
  },
  "a_comp_cor_128": {
    "CumulativeVarianceExplained": 0.3660542945,
    "Mask": "combined",
    "Method": "aCompCor",
    "Retained": true,
    "SingularValue": 114.8660949403,
    "VarianceExplained": 0.0023192903
  },
  "a_comp_cor_129": {
    "CumulativeVarianceExplained": 0.368370465,
    "Mask": "combined",
    "Method": "aCompCor",
    "Retained": true,
    "SingularValue": 114.7888113189,
    "VarianceExplained": 0.0023161704
  },
  "a_comp_cor_13": {
    "CumulativeVarianceExplained": 0.0693312273,
    "Mask": "combined",
    "Method": "aCompCor",
    "Retained": true,
    "SingularValue": 135.1832845659,
    "VarianceExplained": 0.0032123095
  },
  "a_comp_cor_130": {
    "CumulativeVarianceExplained": 0.3706841662,
    "Mask": "combined",
    "Method": "aCompCor",
    "Retained": true,
    "SingularValue": 114.7276078518,
    "VarianceExplained": 0.0023137012
  },
  "a_comp_cor_131": {
    "CumulativeVarianceExplained": 0.3729970976,
    "Mask": "combined",
    "Method": "aCompCor",
    "Retained": true,
    "SingularValue": 114.7085209377,
    "VarianceExplained": 0.0023129314
  },
  "a_comp_cor_132": {
    "CumulativeVarianceExplained": 0.3753047877,
    "Mask": "combined",
    "Method": "aCompCor",
    "Retained": true,
    "SingularValue": 114.5784781767,
    "VarianceExplained": 0.0023076901
  },
  "a_comp_cor_133": {
    "CumulativeVarianceExplained": 0.3776110327,
    "Mask": "combined",
    "Method": "aCompCor",
    "Retained": true,
    "SingularValue": 114.5425965604,
    "VarianceExplained": 0.002306245
  },
  "a_comp_cor_134": {
    "CumulativeVarianceExplained": 0.3799081647,
    "Mask": "combined",
    "Method": "aCompCor",
    "Retained": true,
    "SingularValue": 114.3160668923,
    "VarianceExplained": 0.002297132
  },
  "a_comp_cor_135": {
    "CumulativeVarianceExplained": 0.3822014994,
    "Mask": "combined",
    "Method": "aCompCor",
    "Retained": true,
    "SingularValue": 114.2215451502,
    "VarianceExplained": 0.0022933348
  },
  "a_comp_cor_136": {
    "CumulativeVarianceExplained": 0.3844924994,
    "Mask": "combined",
    "Method": "aCompCor",
    "Retained": true,
    "SingularValue": 114.1633868581,
    "VarianceExplained": 0.002291
  },
  "a_comp_cor_137": {
    "CumulativeVarianceExplained": 0.3867773259,
    "Mask": "combined",
    "Method": "aCompCor",
    "Retained": true,
    "SingularValue": 114.0094673551,
    "VarianceExplained": 0.0022848265
  },
  "a_comp_cor_138": {
    "CumulativeVarianceExplained": 0.3890605162,
    "Mask": "combined",
    "Method": "aCompCor",
    "Retained": true,
    "SingularValue": 113.9686365104,
    "VarianceExplained": 0.0022831902
  },
  "a_comp_cor_139": {
    "CumulativeVarianceExplained": 0.3913404721,
    "Mask": "combined",
    "Method": "aCompCor",
    "Retained": true,
    "SingularValue": 113.8878853297,
    "VarianceExplained": 0.0022799559
  },
  "a_comp_cor_14": {
    "CumulativeVarianceExplained": 0.0724526023,
    "Mask": "combined",
    "Method": "aCompCor",
    "Retained": true,
    "SingularValue": 133.2561539663,
    "VarianceExplained": 0.003121375
  },
  "a_comp_cor_140": {
    "CumulativeVarianceExplained": 0.3936145404,
    "Mask": "combined",
    "Method": "aCompCor",
    "Retained": true,
    "SingularValue": 113.7407421238,
    "VarianceExplained": 0.0022740683
  },
  "a_comp_cor_141": {
    "CumulativeVarianceExplained": 0.3958854395,
    "Mask": "combined",
    "Method": "aCompCor",
    "Retained": true,
    "SingularValue": 113.6614557624,
    "VarianceExplained": 0.002270899
  },
  "a_comp_cor_142": {
    "CumulativeVarianceExplained": 0.3981532633,
    "Mask": "combined",
    "Method": "aCompCor",
    "Retained": true,
    "SingularValue": 113.5844723641,
    "VarianceExplained": 0.0022678239
  },
  "a_comp_cor_143": {
    "CumulativeVarianceExplained": 0.4004197323,
    "Mask": "combined",
    "Method": "aCompCor",
    "Retained": true,
    "SingularValue": 113.550536289,
    "VarianceExplained": 0.002266469
  },
  "a_comp_cor_144": {
    "CumulativeVarianceExplained": 0.4026843732,
    "Mask": "combined",
    "Method": "aCompCor",
    "Retained": true,
    "SingularValue": 113.5047340435,
    "VarianceExplained": 0.0022646409
  },
  "a_comp_cor_145": {
    "CumulativeVarianceExplained": 0.4049465117,
    "Mask": "combined",
    "Method": "aCompCor",
    "Retained": true,
    "SingularValue": 113.4420074325,
    "VarianceExplained": 0.0022621386
  },
  "a_comp_cor_146": {
    "CumulativeVarianceExplained": 0.4072055416,
    "Mask": "combined",
    "Method": "aCompCor",
    "Retained": true,
    "SingularValue": 113.3640341905,
    "VarianceExplained": 0.0022590299
  },
  "a_comp_cor_147": {
    "CumulativeVarianceExplained": 0.409459656,
    "Mask": "combined",
    "Method": "aCompCor",
    "Retained": true,
    "SingularValue": 113.2406291051,
    "VarianceExplained": 0.0022541143
  },
  "a_comp_cor_148": {
    "CumulativeVarianceExplained": 0.4117112884,
    "Mask": "combined",
    "Method": "aCompCor",
    "Retained": true,
    "SingularValue": 113.1782707557,
    "VarianceExplained": 0.0022516325
  },
  "a_comp_cor_149": {
    "CumulativeVarianceExplained": 0.4139589714,
    "Mask": "combined",
    "Method": "aCompCor",
    "Retained": true,
    "SingularValue": 113.0789668899,
    "VarianceExplained": 0.002247683
  },
  "a_comp_cor_15": {
    "CumulativeVarianceExplained": 0.07553774,
    "Mask": "combined",
    "Method": "aCompCor",
    "Retained": true,
    "SingularValue": 132.4803847551,
    "VarianceExplained": 0.0030851377
  },
  "a_comp_cor_150": {
    "CumulativeVarianceExplained": 0.4162035709,
    "Mask": "combined",
    "Method": "aCompCor",
    "Retained": true,
    "SingularValue": 113.0013749954,
    "VarianceExplained": 0.0022445994
  },
  "a_comp_cor_151": {
    "CumulativeVarianceExplained": 0.418445486,
    "Mask": "combined",
    "Method": "aCompCor",
    "Retained": true,
    "SingularValue": 112.9337846205,
    "VarianceExplained": 0.0022419151
  },
  "a_comp_cor_152": {
    "CumulativeVarianceExplained": 0.4206832472,
    "Mask": "combined",
    "Method": "aCompCor",
    "Retained": true,
    "SingularValue": 112.8291131627,
    "VarianceExplained": 0.0022377612
  },
  "a_comp_cor_153": {
    "CumulativeVarianceExplained": 0.4229180365,
    "Mask": "combined",
    "Method": "aCompCor",
    "Retained": true,
    "SingularValue": 112.754165701,
    "VarianceExplained": 0.0022347893
  },
  "a_comp_cor_154": {
    "CumulativeVarianceExplained": 0.4251471751,
    "Mask": "combined",
    "Method": "aCompCor",
    "Retained": true,
    "SingularValue": 112.6115256653,
    "VarianceExplained": 0.0022291386
  },
  "a_comp_cor_155": {
    "CumulativeVarianceExplained": 0.4273740646,
    "Mask": "combined",
    "Method": "aCompCor",
    "Retained": true,
    "SingularValue": 112.5546993474,
    "VarianceExplained": 0.0022268895
  },
  "a_comp_cor_156": {
    "CumulativeVarianceExplained": 0.4295971319,
    "Mask": "combined",
    "Method": "aCompCor",
    "Retained": true,
    "SingularValue": 112.4580661668,
    "VarianceExplained": 0.0022230673
  },
  "a_comp_cor_157": {
    "CumulativeVarianceExplained": 0.431816954,
    "Mask": "combined",
    "Method": "aCompCor",
    "Retained": true,
    "SingularValue": 112.3759510306,
    "VarianceExplained": 0.002219822
  },
  "a_comp_cor_158": {
    "CumulativeVarianceExplained": 0.4340345987,
    "Mask": "combined",
    "Method": "aCompCor",
    "Retained": true,
    "SingularValue": 112.3208263932,
    "VarianceExplained": 0.0022176447
  },
  "a_comp_cor_159": {
    "CumulativeVarianceExplained": 0.4362448008,
    "Mask": "combined",
    "Method": "aCompCor",
    "Retained": true,
    "SingularValue": 112.1321873742,
    "VarianceExplained": 0.0022102021
  },
  "a_comp_cor_16": {
    "CumulativeVarianceExplained": 0.0786056701,
    "Mask": "combined",
    "Method": "aCompCor",
    "Retained": true,
    "SingularValue": 132.1104071214,
    "VarianceExplained": 0.0030679301
  },
  "a_comp_cor_160": {
    "CumulativeVarianceExplained": 0.4384536247,
    "Mask": "combined",
    "Method": "aCompCor",
    "Retained": true,
    "SingularValue": 112.0972232343,
    "VarianceExplained": 0.002208824
  },
  "a_comp_cor_161": {
    "CumulativeVarianceExplained": 0.4406563286,
    "Mask": "combined",
    "Method": "aCompCor",
    "Retained": true,
    "SingularValue": 111.9418185381,
    "VarianceExplained": 0.0022027038
  },
  "a_comp_cor_162": {
    "CumulativeVarianceExplained": 0.4428556484,
    "Mask": "combined",
    "Method": "aCompCor",
    "Retained": true,
    "SingularValue": 111.855795912,
    "VarianceExplained": 0.0021993198
  },
  "a_comp_cor_163": {
    "CumulativeVarianceExplained": 0.445050918,
    "Mask": "combined",
    "Method": "aCompCor",
    "Retained": true,
    "SingularValue": 111.7527547597,
    "VarianceExplained": 0.0021952696
  },
  "a_comp_cor_164": {
    "CumulativeVarianceExplained": 0.4472434386,
    "Mask": "combined",
    "Method": "aCompCor",
    "Retained": true,
    "SingularValue": 111.6827611533,
    "VarianceExplained": 0.0021925206
  },
  "a_comp_cor_165": {
    "CumulativeVarianceExplained": 0.4494327167,
    "Mask": "combined",
    "Method": "aCompCor",
    "Retained": true,
    "SingularValue": 111.6001487955,
    "VarianceExplained": 0.0021892781
  },
  "a_comp_cor_166": {
    "CumulativeVarianceExplained": 0.4516191026,
    "Mask": "combined",
    "Method": "aCompCor",
    "Retained": true,
    "SingularValue": 111.526406023,
    "VarianceExplained": 0.0021863859
  },
  "a_comp_cor_167": {
    "CumulativeVarianceExplained": 0.4538049287,
    "Mask": "combined",
    "Method": "aCompCor",
    "Retained": true,
    "SingularValue": 111.5121295637,
    "VarianceExplained": 0.0021858261
  },
  "a_comp_cor_168": {
    "CumulativeVarianceExplained": 0.4559863715,
    "Mask": "combined",
    "Method": "aCompCor",
    "Retained": true,
    "SingularValue": 111.4002633885,
    "VarianceExplained": 0.0021814428
  },
  "a_comp_cor_169": {
    "CumulativeVarianceExplained": 0.4581662401,
    "Mask": "combined",
    "Method": "aCompCor",
    "Retained": true,
    "SingularValue": 111.3600599091,
    "VarianceExplained": 0.0021798686
  },
  "a_comp_cor_17": {
    "CumulativeVarianceExplained": 0.0816004004,
    "Mask": "combined",
    "Method": "aCompCor",
    "Retained": true,
    "SingularValue": 130.5248390468,
    "VarianceExplained": 0.0029947304
  },
  "a_comp_cor_170": {
    "CumulativeVarianceExplained": 0.4603442519,
    "Mask": "combined",
    "Method": "aCompCor",
    "Retained": true,
    "SingularValue": 111.3126231916,
    "VarianceExplained": 0.0021780118
  },
  "a_comp_cor_171": {
    "CumulativeVarianceExplained": 0.4625199205,
    "Mask": "combined",
    "Method": "aCompCor",
    "Retained": true,
    "SingularValue": 111.2527308403,
    "VarianceExplained": 0.0021756687
  },
  "a_comp_cor_172": {
    "CumulativeVarianceExplained": 0.4646904907,
    "Mask": "combined",
    "Method": "aCompCor",
    "Retained": true,
    "SingularValue": 111.1222991412,
    "VarianceExplained": 0.0021705702
  },
  "a_comp_cor_173": {
    "CumulativeVarianceExplained": 0.4668594713,
    "Mask": "combined",
    "Method": "aCompCor",
    "Retained": true,
    "SingularValue": 111.0816015236,
    "VarianceExplained": 0.0021689806
  },
  "a_comp_cor_174": {
    "CumulativeVarianceExplained": 0.4690250205,
    "Mask": "combined",
    "Method": "aCompCor",
    "Retained": true,
    "SingularValue": 110.9937007034,
    "VarianceExplained": 0.0021655492
  },
  "a_comp_cor_175": {
    "CumulativeVarianceExplained": 0.4711882624,
    "Mask": "combined",
    "Method": "aCompCor",
    "Retained": true,
    "SingularValue": 110.9345560991,
    "VarianceExplained": 0.0021632419
  },
  "a_comp_cor_176": {
    "CumulativeVarianceExplained": 0.4733476077,
    "Mask": "combined",
    "Method": "aCompCor",
    "Retained": true,
    "SingularValue": 110.8345970934,
    "VarianceExplained": 0.0021593453
  },
  "a_comp_cor_177": {
    "CumulativeVarianceExplained": 0.4755047225,
    "Mask": "combined",
    "Method": "aCompCor",
    "Retained": true,
    "SingularValue": 110.7773393917,
    "VarianceExplained": 0.0021571148
  },
  "a_comp_cor_178": {
    "CumulativeVarianceExplained": 0.4776598378,
    "Mask": "combined",
    "Method": "aCompCor",
    "Retained": true,
    "SingularValue": 110.7259860937,
    "VarianceExplained": 0.0021551153
  },
  "a_comp_cor_179": {
    "CumulativeVarianceExplained": 0.4798127024,
    "Mask": "combined",
    "Method": "aCompCor",
    "Retained": true,
    "SingularValue": 110.6681529204,
    "VarianceExplained": 0.0021528646
  },
  "a_comp_cor_18": {
    "CumulativeVarianceExplained": 0.0845826735,
    "Mask": "combined",
    "Method": "aCompCor",
    "Retained": true,
    "SingularValue": 130.2530819791,
    "VarianceExplained": 0.0029822731
  },
  "a_comp_cor_180": {
    "CumulativeVarianceExplained": 0.481958075,
    "Mask": "combined",
    "Method": "aCompCor",
    "Retained": true,
    "SingularValue": 110.4754231366,
    "VarianceExplained": 0.0021453727
  },
  "a_comp_cor_181": {
    "CumulativeVarianceExplained": 0.4841011984,
    "Mask": "combined",
    "Method": "aCompCor",
    "Retained": true,
    "SingularValue": 110.4174930528,
    "VarianceExplained": 0.0021431233
  },
  "a_comp_cor_182": {
    "CumulativeVarianceExplained": 0.4862434348,
    "Mask": "combined",
    "Method": "aCompCor",
    "Retained": true,
    "SingularValue": 110.3946453585,
    "VarianceExplained": 0.0021422365
  },
  "a_comp_cor_183": {
    "CumulativeVarianceExplained": 0.488381619,
    "Mask": "combined",
    "Method": "aCompCor",
    "Retained": true,
    "SingularValue": 110.2901830383,
    "VarianceExplained": 0.0021381842
  },
  "a_comp_cor_184": {
    "CumulativeVarianceExplained": 0.4905176345,
    "Mask": "combined",
    "Method": "aCompCor",
    "Retained": true,
    "SingularValue": 110.2342373585,
    "VarianceExplained": 0.0021360155
  },
  "a_comp_cor_185": {
    "CumulativeVarianceExplained": 0.4926500697,
    "Mask": "combined",
    "Method": "aCompCor",
    "Retained": true,
    "SingularValue": 110.1418135982,
    "VarianceExplained": 0.0021324352
  },
  "a_comp_cor_186": {
    "CumulativeVarianceExplained": 0.4947799853,
    "Mask": "combined",
    "Method": "aCompCor",
    "Retained": true,
    "SingularValue": 110.0767256883,
    "VarianceExplained": 0.0021299156
  },
  "a_comp_cor_187": {
    "CumulativeVarianceExplained": 0.4969074024,
    "Mask": "combined",
    "Method": "aCompCor",
    "Retained": true,
    "SingularValue": 110.0121422249,
    "VarianceExplained": 0.0021274171
  },
  "a_comp_cor_188": {
    "CumulativeVarianceExplained": 0.4990334867,
    "Mask": "combined",
    "Method": "aCompCor",
    "Retained": true,
    "SingularValue": 109.9776764239,
    "VarianceExplained": 0.0021260843
  },
  "a_comp_cor_189": {
    "CumulativeVarianceExplained": 0.50115718,
    "Mask": "combined",
    "Method": "aCompCor",
    "Retained": true,
    "SingularValue": 109.9158209908,
    "VarianceExplained": 0.0021236934
  },
  "a_comp_cor_19": {
    "CumulativeVarianceExplained": 0.0875196586,
    "Mask": "combined",
    "Method": "aCompCor",
    "Retained": true,
    "SingularValue": 129.2603032147,
    "VarianceExplained": 0.002936985
  },
  "a_comp_cor_20": {
    "CumulativeVarianceExplained": 0.0904398165,
    "Mask": "combined",
    "Method": "aCompCor",
    "Retained": true,
    "SingularValue": 128.8894800324,
    "VarianceExplained": 0.0029201579
  },
  "a_comp_cor_21": {
    "CumulativeVarianceExplained": 0.0933389067,
    "Mask": "combined",
    "Method": "aCompCor",
    "Retained": true,
    "SingularValue": 128.4236974886,
    "VarianceExplained": 0.0028990902
  },
  "a_comp_cor_22": {
    "CumulativeVarianceExplained": 0.0962212211,
    "Mask": "combined",
    "Method": "aCompCor",
    "Retained": true,
    "SingularValue": 128.0515909772,
    "VarianceExplained": 0.0028823144
  },
  "a_comp_cor_23": {
    "CumulativeVarianceExplained": 0.099093689,
    "Mask": "combined",
    "Method": "aCompCor",
    "Retained": true,
    "SingularValue": 127.8326783259,
    "VarianceExplained": 0.0028724678
  },
  "a_comp_cor_24": {
    "CumulativeVarianceExplained": 0.1019467243,
    "Mask": "combined",
    "Method": "aCompCor",
    "Retained": true,
    "SingularValue": 127.3995448552,
    "VarianceExplained": 0.0028530353
  },
  "a_comp_cor_25": {
    "CumulativeVarianceExplained": 0.1047910271,
    "Mask": "combined",
    "Method": "aCompCor",
    "Retained": true,
    "SingularValue": 127.2044243207,
    "VarianceExplained": 0.0028443028
  },
  "a_comp_cor_26": {
    "CumulativeVarianceExplained": 0.1076183358,
    "Mask": "combined",
    "Method": "aCompCor",
    "Retained": true,
    "SingularValue": 126.8238461154,
    "VarianceExplained": 0.0028273087
  },
  "a_comp_cor_27": {
    "CumulativeVarianceExplained": 0.1104338513,
    "Mask": "combined",
    "Method": "aCompCor",
    "Retained": true,
    "SingularValue": 126.559066944,
    "VarianceExplained": 0.0028155155
  },
  "a_comp_cor_28": {
    "CumulativeVarianceExplained": 0.1132474795,
    "Mask": "combined",
    "Method": "aCompCor",
    "Retained": true,
    "SingularValue": 126.5166411671,
    "VarianceExplained": 0.0028136282
  },
  "a_comp_cor_29": {
    "CumulativeVarianceExplained": 0.1160480599,
    "Mask": "combined",
    "Method": "aCompCor",
    "Retained": true,
    "SingularValue": 126.2229508676,
    "VarianceExplained": 0.0028005805
  },
  "a_comp_cor_30": {
    "CumulativeVarianceExplained": 0.118841093,
    "Mask": "combined",
    "Method": "aCompCor",
    "Retained": true,
    "SingularValue": 126.0527539435,
    "VarianceExplained": 0.002793033
  },
  "a_comp_cor_31": {
    "CumulativeVarianceExplained": 0.1216239668,
    "Mask": "combined",
    "Method": "aCompCor",
    "Retained": true,
    "SingularValue": 125.8232977862,
    "VarianceExplained": 0.0027828739
  },
  "a_comp_cor_32": {
    "CumulativeVarianceExplained": 0.1244012023,
    "Mask": "combined",
    "Method": "aCompCor",
    "Retained": true,
    "SingularValue": 125.6957674408,
    "VarianceExplained": 0.0027772355
  },
  "a_comp_cor_33": {
    "CumulativeVarianceExplained": 0.127176088,
    "Mask": "combined",
    "Method": "aCompCor",
    "Retained": true,
    "SingularValue": 125.6425812668,
    "VarianceExplained": 0.0027748857
  },
  "a_comp_cor_34": {
    "CumulativeVarianceExplained": 0.1299333727,
    "Mask": "combined",
    "Method": "aCompCor",
    "Retained": true,
    "SingularValue": 125.243474718,
    "VarianceExplained": 0.0027572847
  },
  "a_comp_cor_35": {
    "CumulativeVarianceExplained": 0.1326848952,
    "Mask": "combined",
    "Method": "aCompCor",
    "Retained": true,
    "SingularValue": 125.112540525,
    "VarianceExplained": 0.0027515226
  },
  "a_comp_cor_36": {
    "CumulativeVarianceExplained": 0.1354287813,
    "Mask": "combined",
    "Method": "aCompCor",
    "Retained": true,
    "SingularValue": 124.9388023773,
    "VarianceExplained": 0.0027438861
  },
  "a_comp_cor_37": {
    "CumulativeVarianceExplained": 0.1381671747,
    "Mask": "combined",
    "Method": "aCompCor",
    "Retained": true,
    "SingularValue": 124.8136910135,
    "VarianceExplained": 0.0027383935
  },
  "a_comp_cor_38": {
    "CumulativeVarianceExplained": 0.140899334,
    "Mask": "combined",
    "Method": "aCompCor",
    "Retained": true,
    "SingularValue": 124.6715357111,
    "VarianceExplained": 0.0027321593
  },
  "a_comp_cor_39": {
    "CumulativeVarianceExplained": 0.1436261107,
    "Mask": "combined",
    "Method": "aCompCor",
    "Retained": true,
    "SingularValue": 124.5486674017,
    "VarianceExplained": 0.0027267766
  },
  "a_comp_cor_40": {
    "CumulativeVarianceExplained": 0.1463414964,
    "Mask": "combined",
    "Method": "aCompCor",
    "Retained": true,
    "SingularValue": 124.288248891,
    "VarianceExplained": 0.0027153857
  },
  "a_comp_cor_41": {
    "CumulativeVarianceExplained": 0.1490507139,
    "Mask": "combined",
    "Method": "aCompCor",
    "Retained": true,
    "SingularValue": 124.1470031107,
    "VarianceExplained": 0.0027092175
  },
  "a_comp_cor_42": {
    "CumulativeVarianceExplained": 0.1517509576,
    "Mask": "combined",
    "Method": "aCompCor",
    "Retained": true,
    "SingularValue": 123.9412239203,
    "VarianceExplained": 0.0027002437
  },
  "a_comp_cor_43": {
    "CumulativeVarianceExplained": 0.1544465735,
    "Mask": "combined",
    "Method": "aCompCor",
    "Retained": true,
    "SingularValue": 123.8349715651,
    "VarianceExplained": 0.0026956159
  },
  "a_comp_cor_44": {
    "CumulativeVarianceExplained": 0.1571358578,
    "Mask": "combined",
    "Method": "aCompCor",
    "Retained": true,
    "SingularValue": 123.6894504353,
    "VarianceExplained": 0.0026892843
  },
  "a_comp_cor_45": {
    "CumulativeVarianceExplained": 0.1598226169,
    "Mask": "combined",
    "Method": "aCompCor",
    "Retained": true,
    "SingularValue": 123.6313666356,
    "VarianceExplained": 0.0026867591
  },
  "a_comp_cor_46": {
    "CumulativeVarianceExplained": 0.1624996128,
    "Mask": "combined",
    "Method": "aCompCor",
    "Retained": true,
    "SingularValue": 123.4065335221,
    "VarianceExplained": 0.0026769959
  },
  "a_comp_cor_47": {
    "CumulativeVarianceExplained": 0.1651705095,
    "Mask": "combined",
    "Method": "aCompCor",
    "Retained": true,
    "SingularValue": 123.2658716674,
    "VarianceExplained": 0.0026708967
  },
  "a_comp_cor_48": {
    "CumulativeVarianceExplained": 0.1678358117,
    "Mask": "combined",
    "Method": "aCompCor",
    "Retained": true,
    "SingularValue": 123.1367049376,
    "VarianceExplained": 0.0026653022
  },
  "a_comp_cor_49": {
    "CumulativeVarianceExplained": 0.1704969659,
    "Mask": "combined",
    "Method": "aCompCor",
    "Retained": true,
    "SingularValue": 123.0408497514,
    "VarianceExplained": 0.0026611542
  },
  "a_comp_cor_50": {
    "CumulativeVarianceExplained": 0.1731535749,
    "Mask": "combined",
    "Method": "aCompCor",
    "Retained": true,
    "SingularValue": 122.9357290221,
    "VarianceExplained": 0.002656609
  },
  "a_comp_cor_51": {
    "CumulativeVarianceExplained": 0.175807388,
    "Mask": "combined",
    "Method": "aCompCor",
    "Retained": true,
    "SingularValue": 122.871021566,
    "VarianceExplained": 0.0026538131
  },
  "a_comp_cor_52": {
    "CumulativeVarianceExplained": 0.1784540397,
    "Mask": "combined",
    "Method": "aCompCor",
    "Retained": true,
    "SingularValue": 122.7051238042,
    "VarianceExplained": 0.0026466517
  },
  "a_comp_cor_53": {
    "CumulativeVarianceExplained": 0.1810969675,
    "Mask": "combined",
    "Method": "aCompCor",
    "Retained": true,
    "SingularValue": 122.6187697941,
    "VarianceExplained": 0.0026429278
  },
  "a_comp_cor_54": {
    "CumulativeVarianceExplained": 0.1837362911,
    "Mask": "combined",
    "Method": "aCompCor",
    "Retained": true,
    "SingularValue": 122.5351329041,
    "VarianceExplained": 0.0026393236
  },
  "a_comp_cor_55": {
    "CumulativeVarianceExplained": 0.186366545,
    "Mask": "combined",
    "Method": "aCompCor",
    "Retained": true,
    "SingularValue": 122.3244112559,
    "VarianceExplained": 0.0026302538
  },
  "a_comp_cor_56": {
    "CumulativeVarianceExplained": 0.1889941268,
    "Mask": "combined",
    "Method": "aCompCor",
    "Retained": true,
    "SingularValue": 122.2622618275,
    "VarianceExplained": 0.0026275818
  },
  "a_comp_cor_57": {
    "CumulativeVarianceExplained": 0.1916164239,
    "Mask": "combined",
    "Method": "aCompCor",
    "Retained": true,
    "SingularValue": 122.1392504342,
    "VarianceExplained": 0.0026222971
  },
  "a_comp_cor_58": {
    "CumulativeVarianceExplained": 0.1942330948,
    "Mask": "combined",
    "Method": "aCompCor",
    "Retained": true,
    "SingularValue": 122.0081530624,
    "VarianceExplained": 0.0026166709
  },
  "a_comp_cor_59": {
    "CumulativeVarianceExplained": 0.1968420915,
    "Mask": "combined",
    "Method": "aCompCor",
    "Retained": true,
    "SingularValue": 121.8291091429,
    "VarianceExplained": 0.0026089967
  },
  "a_comp_cor_60": {
    "CumulativeVarianceExplained": 0.1994470539,
    "Mask": "combined",
    "Method": "aCompCor",
    "Retained": true,
    "SingularValue": 121.7348796903,
    "VarianceExplained": 0.0026049624
  },
  "a_comp_cor_61": {
    "CumulativeVarianceExplained": 0.2020466763,
    "Mask": "combined",
    "Method": "aCompCor",
    "Retained": true,
    "SingularValue": 121.6100421684,
    "VarianceExplained": 0.0025996224
  },
  "a_comp_cor_62": {
    "CumulativeVarianceExplained": 0.2046361763,
    "Mask": "combined",
    "Method": "aCompCor",
    "Retained": true,
    "SingularValue": 121.3730496869,
    "VarianceExplained": 0.0025895
  },
  "a_comp_cor_63": {
    "CumulativeVarianceExplained": 0.2072235096,
    "Mask": "combined",
    "Method": "aCompCor",
    "Retained": true,
    "SingularValue": 121.3222604819,
    "VarianceExplained": 0.0025873333
  },
  "a_comp_cor_64": {
    "CumulativeVarianceExplained": 0.2098051358,
    "Mask": "combined",
    "Method": "aCompCor",
    "Retained": true,
    "SingularValue": 121.1883804063,
    "VarianceExplained": 0.0025816262
  },
  "a_comp_cor_65": {
    "CumulativeVarianceExplained": 0.2123804172,
    "Mask": "combined",
    "Method": "aCompCor",
    "Retained": true,
    "SingularValue": 121.0393685407,
    "VarianceExplained": 0.0025752814
  },
  "a_comp_cor_66": {
    "CumulativeVarianceExplained": 0.2149523678,
    "Mask": "combined",
    "Method": "aCompCor",
    "Retained": true,
    "SingularValue": 120.9610675636,
    "VarianceExplained": 0.0025719506
  },
  "a_comp_cor_67": {
    "CumulativeVarianceExplained": 0.2175199503,
    "Mask": "combined",
    "Method": "aCompCor",
    "Retained": true,
    "SingularValue": 120.8583073621,
    "VarianceExplained": 0.0025675825
  },
  "a_comp_cor_68": {
    "CumulativeVarianceExplained": 0.2200845637,
    "Mask": "combined",
    "Method": "aCompCor",
    "Retained": true,
    "SingularValue": 120.7884060922,
    "VarianceExplained": 0.0025646133
  },
  "a_comp_cor_69": {
    "CumulativeVarianceExplained": 0.2226446728,
    "Mask": "combined",
    "Method": "aCompCor",
    "Retained": true,
    "SingularValue": 120.6822910034,
    "VarianceExplained": 0.0025601092
  },
  "a_comp_cor_70": {
    "CumulativeVarianceExplained": 0.225198128,
    "Mask": "combined",
    "Method": "aCompCor",
    "Retained": true,
    "SingularValue": 120.5253541588,
    "VarianceExplained": 0.0025534551
  },
  "a_comp_cor_71": {
    "CumulativeVarianceExplained": 0.2277506658,
    "Mask": "combined",
    "Method": "aCompCor",
    "Retained": true,
    "SingularValue": 120.5037053717,
    "VarianceExplained": 0.0025525379
  },
  "a_comp_cor_72": {
    "CumulativeVarianceExplained": 0.2303025583,
    "Mask": "combined",
    "Method": "aCompCor",
    "Retained": true,
    "SingularValue": 120.4884681807,
    "VarianceExplained": 0.0025518924
  },
  "a_comp_cor_73": {
    "CumulativeVarianceExplained": 0.2328503718,
    "Mask": "combined",
    "Method": "aCompCor",
    "Retained": true,
    "SingularValue": 120.3921374589,
    "VarianceExplained": 0.0025478136
  },
  "a_comp_cor_74": {
    "CumulativeVarianceExplained": 0.2353888825,
    "Mask": "combined",
    "Method": "aCompCor",
    "Retained": true,
    "SingularValue": 120.1721414066,
    "VarianceExplained": 0.0025385107
  },
  "a_comp_cor_75": {
    "CumulativeVarianceExplained": 0.2379195283,
    "Mask": "combined",
    "Method": "aCompCor",
    "Retained": true,
    "SingularValue": 119.9858374682,
    "VarianceExplained": 0.0025306458
  },
  "a_comp_cor_76": {
    "CumulativeVarianceExplained": 0.2404413527,
    "Mask": "combined",
    "Method": "aCompCor",
    "Retained": true,
    "SingularValue": 119.7765274479,
    "VarianceExplained": 0.0025218243
  },
  "a_comp_cor_77": {
    "CumulativeVarianceExplained": 0.2429593863,
    "Mask": "combined",
    "Method": "aCompCor",
    "Retained": true,
    "SingularValue": 119.6864723948,
    "VarianceExplained": 0.0025180336
  },
  "a_comp_cor_78": {
    "CumulativeVarianceExplained": 0.2454742897,
    "Mask": "combined",
    "Method": "aCompCor",
    "Retained": true,
    "SingularValue": 119.6120571271,
    "VarianceExplained": 0.0025149034
  },
  "a_comp_cor_79": {
    "CumulativeVarianceExplained": 0.2479834774,
    "Mask": "combined",
    "Method": "aCompCor",
    "Retained": true,
    "SingularValue": 119.4760547022,
    "VarianceExplained": 0.0025091876
  },
  "a_comp_cor_80": {
    "CumulativeVarianceExplained": 0.2504892837,
    "Mask": "combined",
    "Method": "aCompCor",
    "Retained": true,
    "SingularValue": 119.3955251986,
    "VarianceExplained": 0.0025058063
  },
  "a_comp_cor_81": {
    "CumulativeVarianceExplained": 0.2529937436,
    "Mask": "combined",
    "Method": "aCompCor",
    "Retained": true,
    "SingularValue": 119.3634440321,
    "VarianceExplained": 0.0025044599
  },
  "a_comp_cor_82": {
    "CumulativeVarianceExplained": 0.255492374,
    "Mask": "combined",
    "Method": "aCompCor",
    "Retained": true,
    "SingularValue": 119.2244475006,
    "VarianceExplained": 0.0024986305
  },
  "a_comp_cor_83": {
    "CumulativeVarianceExplained": 0.25798465,
    "Mask": "combined",
    "Method": "aCompCor",
    "Retained": true,
    "SingularValue": 119.0727451721,
    "VarianceExplained": 0.002492276
  },
  "a_comp_cor_84": {
    "CumulativeVarianceExplained": 0.2604705491,
    "Mask": "combined",
    "Method": "aCompCor",
    "Retained": true,
    "SingularValue": 118.9203159843,
    "VarianceExplained": 0.0024858991
  },
  "a_comp_cor_85": {
    "CumulativeVarianceExplained": 0.2629515172,
    "Mask": "combined",
    "Method": "aCompCor",
    "Retained": true,
    "SingularValue": 118.8023127678,
    "VarianceExplained": 0.0024809681
  },
  "a_comp_cor_86": {
    "CumulativeVarianceExplained": 0.2654281227,
    "Mask": "combined",
    "Method": "aCompCor",
    "Retained": true,
    "SingularValue": 118.6978125268,
    "VarianceExplained": 0.0024766055
  },
  "a_comp_cor_87": {
    "CumulativeVarianceExplained": 0.2679007538,
    "Mask": "combined",
    "Method": "aCompCor",
    "Retained": true,
    "SingularValue": 118.6025327818,
    "VarianceExplained": 0.0024726311
  },
  "a_comp_cor_88": {
    "CumulativeVarianceExplained": 0.2703704422,
    "Mask": "combined",
    "Method": "aCompCor",
    "Retained": true,
    "SingularValue": 118.5319391262,
    "VarianceExplained": 0.0024696885
  },
  "a_comp_cor_89": {
    "CumulativeVarianceExplained": 0.2728372121,
    "Mask": "combined",
    "Method": "aCompCor",
    "Retained": true,
    "SingularValue": 118.4618802528,
    "VarianceExplained": 0.0024667699
  },
  "a_comp_cor_90": {
    "CumulativeVarianceExplained": 0.2753014903,
    "Mask": "combined",
    "Method": "aCompCor",
    "Retained": true,
    "SingularValue": 118.4020342272,
    "VarianceExplained": 0.0024642781
  },
  "a_comp_cor_91": {
    "CumulativeVarianceExplained": 0.2777621245,
    "Mask": "combined",
    "Method": "aCompCor",
    "Retained": true,
    "SingularValue": 118.3144634001,
    "VarianceExplained": 0.0024606343
  },
  "a_comp_cor_92": {
    "CumulativeVarianceExplained": 0.2802215733,
    "Mask": "combined",
    "Method": "aCompCor",
    "Retained": true,
    "SingularValue": 118.2859568401,
    "VarianceExplained": 0.0024594487
  },
  "a_comp_cor_93": {
    "CumulativeVarianceExplained": 0.2826737323,
    "Mask": "combined",
    "Method": "aCompCor",
    "Retained": true,
    "SingularValue": 118.1105306116,
    "VarianceExplained": 0.0024521591
  },
  "a_comp_cor_94": {
    "CumulativeVarianceExplained": 0.285125645,
    "Mask": "combined",
    "Method": "aCompCor",
    "Retained": true,
    "SingularValue": 118.10459631,
    "VarianceExplained": 0.0024519126
  },
  "a_comp_cor_95": {
    "CumulativeVarianceExplained": 0.2875719055,
    "Mask": "combined",
    "Method": "aCompCor",
    "Retained": true,
    "SingularValue": 117.9683915575,
    "VarianceExplained": 0.0024462605
  },
  "a_comp_cor_96": {
    "CumulativeVarianceExplained": 0.2900099285,
    "Mask": "combined",
    "Method": "aCompCor",
    "Retained": true,
    "SingularValue": 117.7696006063,
    "VarianceExplained": 0.002438023
  },
  "a_comp_cor_97": {
    "CumulativeVarianceExplained": 0.2924449969,
    "Mask": "combined",
    "Method": "aCompCor",
    "Retained": true,
    "SingularValue": 117.6982178818,
    "VarianceExplained": 0.0024350684
  },
  "a_comp_cor_98": {
    "CumulativeVarianceExplained": 0.2948771645,
    "Mask": "combined",
    "Method": "aCompCor",
    "Retained": true,
    "SingularValue": 117.6280903608,
    "VarianceExplained": 0.0024321675
  },
  "a_comp_cor_99": {
    "CumulativeVarianceExplained": 0.2973075778,
    "Mask": "combined",
    "Method": "aCompCor",
    "Retained": true,
    "SingularValue": 117.5856639499,
    "VarianceExplained": 0.0024304134
  },
  "c_comp_cor_00": {
    "CumulativeVarianceExplained": 0.0572785621,
    "Mask": "CSF",
    "Method": "aCompCor",
    "Retained": true,
    "SingularValue": 137.6882656231,
    "VarianceExplained": 0.0572785621
  },
  "c_comp_cor_01": {
    "CumulativeVarianceExplained": 0.1088283672,
    "Mask": "CSF",
    "Method": "aCompCor",
    "Retained": true,
    "SingularValue": 130.6214166139,
    "VarianceExplained": 0.0515498051
  },
  "c_comp_cor_02": {
    "CumulativeVarianceExplained": 0.152657824,
    "Mask": "CSF",
    "Method": "aCompCor",
    "Retained": true,
    "SingularValue": 120.4436533086,
    "VarianceExplained": 0.0438294568
  },
  "c_comp_cor_03": {
    "CumulativeVarianceExplained": 0.185917603,
    "Mask": "CSF",
    "Method": "aCompCor",
    "Retained": true,
    "SingularValue": 104.9205491578,
    "VarianceExplained": 0.0332597789
  },
  "c_comp_cor_04": {
    "CumulativeVarianceExplained": 0.2075201453,
    "Mask": "CSF",
    "Method": "aCompCor",
    "Retained": true,
    "SingularValue": 84.5577286214,
    "VarianceExplained": 0.0216025424
  },
  "c_comp_cor_05": {
    "CumulativeVarianceExplained": 0.2259325296,
    "Mask": "CSF",
    "Method": "aCompCor",
    "Retained": true,
    "SingularValue": 78.0649149059,
    "VarianceExplained": 0.0184123843
  },
  "c_comp_cor_06": {
    "CumulativeVarianceExplained": 0.2430534103,
    "Mask": "CSF",
    "Method": "aCompCor",
    "Retained": true,
    "SingularValue": 75.277281501,
    "VarianceExplained": 0.0171208807
  },
  "c_comp_cor_07": {
    "CumulativeVarianceExplained": 0.2584537932,
    "Mask": "CSF",
    "Method": "aCompCor",
    "Retained": true,
    "SingularValue": 71.3948089349,
    "VarianceExplained": 0.0154003829
  },
  "c_comp_cor_08": {
    "CumulativeVarianceExplained": 0.2719483044,
    "Mask": "CSF",
    "Method": "aCompCor",
    "Retained": true,
    "SingularValue": 66.8312300502,
    "VarianceExplained": 0.0134945112
  },
  "c_comp_cor_09": {
    "CumulativeVarianceExplained": 0.2841439278,
    "Mask": "CSF",
    "Method": "aCompCor",
    "Retained": true,
    "SingularValue": 63.5335142335,
    "VarianceExplained": 0.0121956234
  },
  "c_comp_cor_10": {
    "CumulativeVarianceExplained": 0.2957612534,
    "Mask": "CSF",
    "Method": "aCompCor",
    "Retained": true,
    "SingularValue": 62.0088899143,
    "VarianceExplained": 0.0116173256
  },
  "c_comp_cor_11": {
    "CumulativeVarianceExplained": 0.3064816359,
    "Mask": "CSF",
    "Method": "aCompCor",
    "Retained": true,
    "SingularValue": 59.5670393901,
    "VarianceExplained": 0.0107203824
  },
  "c_comp_cor_12": {
    "CumulativeVarianceExplained": 0.3163704584,
    "Mask": "CSF",
    "Method": "aCompCor",
    "Retained": true,
    "SingularValue": 57.2101607486,
    "VarianceExplained": 0.0098888226
  },
  "c_comp_cor_13": {
    "CumulativeVarianceExplained": 0.325697984,
    "Mask": "CSF",
    "Method": "aCompCor",
    "Retained": true,
    "SingularValue": 55.5627969663,
    "VarianceExplained": 0.0093275256
  },
  "c_comp_cor_14": {
    "CumulativeVarianceExplained": 0.3346176688,
    "Mask": "CSF",
    "Method": "aCompCor",
    "Retained": true,
    "SingularValue": 54.3344943159,
    "VarianceExplained": 0.0089196848
  },
  "c_comp_cor_15": {
    "CumulativeVarianceExplained": 0.3426434714,
    "Mask": "CSF",
    "Method": "aCompCor",
    "Retained": true,
    "SingularValue": 51.5400829311,
    "VarianceExplained": 0.0080258026
  },
  "c_comp_cor_16": {
    "CumulativeVarianceExplained": 0.3503174143,
    "Mask": "CSF",
    "Method": "aCompCor",
    "Retained": true,
    "SingularValue": 50.3976352132,
    "VarianceExplained": 0.0076739429
  },
  "c_comp_cor_17": {
    "CumulativeVarianceExplained": 0.3575967722,
    "Mask": "CSF",
    "Method": "aCompCor",
    "Retained": true,
    "SingularValue": 49.0848434307,
    "VarianceExplained": 0.0072793578
  },
  "c_comp_cor_18": {
    "CumulativeVarianceExplained": 0.364654961,
    "Mask": "CSF",
    "Method": "aCompCor",
    "Retained": true,
    "SingularValue": 48.3334185591,
    "VarianceExplained": 0.0070581889
  },
  "c_comp_cor_19": {
    "CumulativeVarianceExplained": 0.3716250582,
    "Mask": "CSF",
    "Method": "aCompCor",
    "Retained": true,
    "SingularValue": 48.0308523622,
    "VarianceExplained": 0.0069700972
  },
  "c_comp_cor_20": {
    "CumulativeVarianceExplained": 0.3783688946,
    "Mask": "CSF",
    "Method": "aCompCor",
    "Retained": true,
    "SingularValue": 47.2448406336,
    "VarianceExplained": 0.0067438364
  },
  "c_comp_cor_21": {
    "CumulativeVarianceExplained": 0.385015371,
    "Mask": "CSF",
    "Method": "aCompCor",
    "Retained": true,
    "SingularValue": 46.9025665378,
    "VarianceExplained": 0.0066464764
  },
  "c_comp_cor_22": {
    "CumulativeVarianceExplained": 0.3915967567,
    "Mask": "CSF",
    "Method": "aCompCor",
    "Retained": true,
    "SingularValue": 46.6723371,
    "VarianceExplained": 0.0065813857
  },
  "c_comp_cor_23": {
    "CumulativeVarianceExplained": 0.3980545465,
    "Mask": "CSF",
    "Method": "aCompCor",
    "Retained": true,
    "SingularValue": 46.2320154834,
    "VarianceExplained": 0.0064577898
  },
  "c_comp_cor_24": {
    "CumulativeVarianceExplained": 0.4039897988,
    "Mask": "CSF",
    "Method": "aCompCor",
    "Retained": true,
    "SingularValue": 44.3221141015,
    "VarianceExplained": 0.0059352523
  },
  "c_comp_cor_25": {
    "CumulativeVarianceExplained": 0.4098229617,
    "Mask": "CSF",
    "Method": "aCompCor",
    "Retained": true,
    "SingularValue": 43.9392793621,
    "VarianceExplained": 0.0058331629
  },
  "c_comp_cor_26": {
    "CumulativeVarianceExplained": 0.4155428743,
    "Mask": "CSF",
    "Method": "aCompCor",
    "Retained": true,
    "SingularValue": 43.5106500228,
    "VarianceExplained": 0.0057199126
  },
  "c_comp_cor_27": {
    "CumulativeVarianceExplained": 0.4211022022,
    "Mask": "CSF",
    "Method": "aCompCor",
    "Retained": true,
    "SingularValue": 42.8955283408,
    "VarianceExplained": 0.0055593279
  },
  "c_comp_cor_28": {
    "CumulativeVarianceExplained": 0.4264890997,
    "Mask": "CSF",
    "Method": "aCompCor",
    "Retained": true,
    "SingularValue": 42.2250556772,
    "VarianceExplained": 0.0053868975
  },
  "c_comp_cor_29": {
    "CumulativeVarianceExplained": 0.4318017266,
    "Mask": "CSF",
    "Method": "aCompCor",
    "Retained": true,
    "SingularValue": 41.932961523,
    "VarianceExplained": 0.0053126269
  },
  "c_comp_cor_30": {
    "CumulativeVarianceExplained": 0.4369866474,
    "Mask": "CSF",
    "Method": "aCompCor",
    "Retained": true,
    "SingularValue": 41.425898728,
    "VarianceExplained": 0.0051849208
  },
  "c_comp_cor_31": {
    "CumulativeVarianceExplained": 0.4420924046,
    "Mask": "CSF",
    "Method": "aCompCor",
    "Retained": true,
    "SingularValue": 41.1084359292,
    "VarianceExplained": 0.0051057572
  },
  "c_comp_cor_32": {
    "CumulativeVarianceExplained": 0.4470868936,
    "Mask": "CSF",
    "Method": "aCompCor",
    "Retained": true,
    "SingularValue": 40.6580372492,
    "VarianceExplained": 0.0049944891
  },
  "c_comp_cor_33": {
    "CumulativeVarianceExplained": 0.4519842079,
    "Mask": "CSF",
    "Method": "aCompCor",
    "Retained": true,
    "SingularValue": 40.2605646974,
    "VarianceExplained": 0.0048973142
  },
  "c_comp_cor_34": {
    "CumulativeVarianceExplained": 0.4567937875,
    "Mask": "CSF",
    "Method": "aCompCor",
    "Retained": true,
    "SingularValue": 39.8983041691,
    "VarianceExplained": 0.0048095797
  },
  "c_comp_cor_35": {
    "CumulativeVarianceExplained": 0.4614748702,
    "Mask": "CSF",
    "Method": "aCompCor",
    "Retained": true,
    "SingularValue": 39.3617166633,
    "VarianceExplained": 0.0046810827
  },
  "c_comp_cor_36": {
    "CumulativeVarianceExplained": 0.4661084288,
    "Mask": "CSF",
    "Method": "aCompCor",
    "Retained": true,
    "SingularValue": 39.1613998547,
    "VarianceExplained": 0.0046335586
  },
  "c_comp_cor_37": {
    "CumulativeVarianceExplained": 0.4706720235,
    "Mask": "CSF",
    "Method": "aCompCor",
    "Retained": true,
    "SingularValue": 38.8646184444,
    "VarianceExplained": 0.0045635947
  },
  "c_comp_cor_38": {
    "CumulativeVarianceExplained": 0.4751989463,
    "Mask": "CSF",
    "Method": "aCompCor",
    "Retained": true,
    "SingularValue": 38.7081503516,
    "VarianceExplained": 0.0045269228
  },
  "c_comp_cor_39": {
    "CumulativeVarianceExplained": 0.4796557332,
    "Mask": "CSF",
    "Method": "aCompCor",
    "Retained": true,
    "SingularValue": 38.4071259305,
    "VarianceExplained": 0.0044567869
  },
  "c_comp_cor_40": {
    "CumulativeVarianceExplained": 0.4840391033,
    "Mask": "CSF",
    "Method": "aCompCor",
    "Retained": true,
    "SingularValue": 38.0894713113,
    "VarianceExplained": 0.0043833701
  },
  "c_comp_cor_41": {
    "CumulativeVarianceExplained": 0.4884045852,
    "Mask": "CSF",
    "Method": "aCompCor",
    "Retained": true,
    "SingularValue": 38.0116719185,
    "VarianceExplained": 0.0043654819
  },
  "c_comp_cor_42": {
    "CumulativeVarianceExplained": 0.4926912444,
    "Mask": "CSF",
    "Method": "aCompCor",
    "Retained": true,
    "SingularValue": 37.666941254,
    "VarianceExplained": 0.0042866592
  },
  "c_comp_cor_43": {
    "CumulativeVarianceExplained": 0.4969313805,
    "Mask": "CSF",
    "Method": "aCompCor",
    "Retained": true,
    "SingularValue": 37.4619840178,
    "VarianceExplained": 0.0042401361
  },
  "c_comp_cor_44": {
    "CumulativeVarianceExplained": 0.5010893016,
    "Mask": "CSF",
    "Method": "aCompCor",
    "Retained": true,
    "SingularValue": 37.0970180653,
    "VarianceExplained": 0.0041579212
  },
  "csf": {
    "Method": "Mean"
  },
  "csf_wm": {
    "Method": "Mean"
  },
  "global_signal": {
    "Method": "Mean"
  },
  "t_comp_cor_00": {
    "CumulativeVarianceExplained": 0.1159648666,
    "Method": "tCompCor",
    "Retained": true,
    "SingularValue": 497.5294856173,
    "VarianceExplained": 0.1159648666
  },
  "t_comp_cor_01": {
    "CumulativeVarianceExplained": 0.2201231737,
    "Method": "tCompCor",
    "Retained": true,
    "SingularValue": 471.5226552135,
    "VarianceExplained": 0.1041583072
  },
  "t_comp_cor_02": {
    "CumulativeVarianceExplained": 0.3192818946,
    "Method": "tCompCor",
    "Retained": true,
    "SingularValue": 460.0669814512,
    "VarianceExplained": 0.0991587209
  },
  "t_comp_cor_03": {
    "CumulativeVarianceExplained": 0.359841443,
    "Method": "tCompCor",
    "Retained": true,
    "SingularValue": 294.2403057757,
    "VarianceExplained": 0.0405595484
  },
  "t_comp_cor_04": {
    "CumulativeVarianceExplained": 0.3979657156,
    "Method": "tCompCor",
    "Retained": true,
    "SingularValue": 285.2701893099,
    "VarianceExplained": 0.0381242725
  },
  "t_comp_cor_05": {
    "CumulativeVarianceExplained": 0.4323260325,
    "Method": "tCompCor",
    "Retained": true,
    "SingularValue": 270.8221543319,
    "VarianceExplained": 0.034360317
  },
  "t_comp_cor_06": {
    "CumulativeVarianceExplained": 0.4573746464,
    "Method": "tCompCor",
    "Retained": true,
    "SingularValue": 231.2317450923,
    "VarianceExplained": 0.0250486139
  },
  "t_comp_cor_07": {
    "CumulativeVarianceExplained": 0.4810116379,
    "Method": "tCompCor",
    "Retained": true,
    "SingularValue": 224.6216982623,
    "VarianceExplained": 0.0236369914
  },
  "t_comp_cor_08": {
    "CumulativeVarianceExplained": 0.5016352477,
    "Method": "tCompCor",
    "Retained": true,
    "SingularValue": 209.8156841825,
    "VarianceExplained": 0.0206236098
  },
  "tcompcor": {
    "Method": "Mean"
  },
  "w_comp_cor_00": {
    "CumulativeVarianceExplained": 0.0096270962,
    "Mask": "WM",
    "Method": "aCompCor",
    "Retained": true,
    "SingularValue": 221.9254712607,
    "VarianceExplained": 0.0096270962
  },
  "w_comp_cor_01": {
    "CumulativeVarianceExplained": 0.016165743,
    "Mask": "WM",
    "Method": "aCompCor",
    "Retained": true,
    "SingularValue": 182.895675015,
    "VarianceExplained": 0.0065386468
  },
  "w_comp_cor_02": {
    "CumulativeVarianceExplained": 0.0217975124,
    "Mask": "WM",
    "Method": "aCompCor",
    "Retained": true,
    "SingularValue": 169.7391126284,
    "VarianceExplained": 0.0056317694
  },
  "w_comp_cor_03": {
    "CumulativeVarianceExplained": 0.0267850106,
    "Mask": "WM",
    "Method": "aCompCor",
    "Retained": true,
    "SingularValue": 159.7352880743,
    "VarianceExplained": 0.0049874982
  },
  "w_comp_cor_04": {
    "CumulativeVarianceExplained": 0.0316812261,
    "Mask": "WM",
    "Method": "aCompCor",
    "Retained": true,
    "SingularValue": 158.2667766176,
    "VarianceExplained": 0.0048962155
  },
  "w_comp_cor_05": {
    "CumulativeVarianceExplained": 0.0363580555,
    "Mask": "WM",
    "Method": "aCompCor",
    "Retained": true,
    "SingularValue": 154.6803911292,
    "VarianceExplained": 0.0046768294
  },
  "w_comp_cor_06": {
    "CumulativeVarianceExplained": 0.0404999417,
    "Mask": "WM",
    "Method": "aCompCor",
    "Retained": true,
    "SingularValue": 145.5655395184,
    "VarianceExplained": 0.0041418862
  },
  "w_comp_cor_07": {
    "CumulativeVarianceExplained": 0.0442321901,
    "Mask": "WM",
    "Method": "aCompCor",
    "Retained": true,
    "SingularValue": 138.1798664049,
    "VarianceExplained": 0.0037322484
  },
  "w_comp_cor_08": {
    "CumulativeVarianceExplained": 0.0478154799,
    "Mask": "WM",
    "Method": "aCompCor",
    "Retained": true,
    "SingularValue": 135.3943251253,
    "VarianceExplained": 0.0035832898
  },
  "w_comp_cor_09": {
    "CumulativeVarianceExplained": 0.0511789554,
    "Mask": "WM",
    "Method": "aCompCor",
    "Retained": true,
    "SingularValue": 131.1757711573,
    "VarianceExplained": 0.0033634754
  },
  "w_comp_cor_10": {
    "CumulativeVarianceExplained": 0.0544859038,
    "Mask": "WM",
    "Method": "aCompCor",
    "Retained": true,
    "SingularValue": 130.0688228906,
    "VarianceExplained": 0.0033069485
  },
  "w_comp_cor_100": {
    "CumulativeVarianceExplained": 0.2976702937,
    "Mask": "WM",
    "Method": "aCompCor",
    "Retained": true,
    "SingularValue": 112.0715140642,
    "VarianceExplained": 0.002455113
  },
  "w_comp_cor_101": {
    "CumulativeVarianceExplained": 0.3001214939,
    "Mask": "WM",
    "Method": "aCompCor",
    "Retained": true,
    "SingularValue": 111.982171422,
    "VarianceExplained": 0.0024512002
  },
  "w_comp_cor_102": {
    "CumulativeVarianceExplained": 0.3025721703,
    "Mask": "WM",
    "Method": "aCompCor",
    "Retained": true,
    "SingularValue": 111.970206355,
    "VarianceExplained": 0.0024506764
  },
  "w_comp_cor_103": {
    "CumulativeVarianceExplained": 0.3050158227,
    "Mask": "WM",
    "Method": "aCompCor",
    "Retained": true,
    "SingularValue": 111.809630565,
    "VarianceExplained": 0.0024436524
  },
  "w_comp_cor_104": {
    "CumulativeVarianceExplained": 0.3074576202,
    "Mask": "WM",
    "Method": "aCompCor",
    "Retained": true,
    "SingularValue": 111.7671871155,
    "VarianceExplained": 0.0024417975
  },
  "w_comp_cor_105": {
    "CumulativeVarianceExplained": 0.3098972566,
    "Mask": "WM",
    "Method": "aCompCor",
    "Retained": true,
    "SingularValue": 111.7177157339,
    "VarianceExplained": 0.0024396364
  },
  "w_comp_cor_106": {
    "CumulativeVarianceExplained": 0.3123316179,
    "Mask": "WM",
    "Method": "aCompCor",
    "Retained": true,
    "SingularValue": 111.5968697376,
    "VarianceExplained": 0.0024343613
  },
  "w_comp_cor_107": {
    "CumulativeVarianceExplained": 0.3147652455,
    "Mask": "WM",
    "Method": "aCompCor",
    "Retained": true,
    "SingularValue": 111.5800515828,
    "VarianceExplained": 0.0024336276
  },
  "w_comp_cor_108": {
    "CumulativeVarianceExplained": 0.3171954204,
    "Mask": "WM",
    "Method": "aCompCor",
    "Retained": true,
    "SingularValue": 111.5008696942,
    "VarianceExplained": 0.0024301748
  },
  "w_comp_cor_109": {
    "CumulativeVarianceExplained": 0.3196207664,
    "Mask": "WM",
    "Method": "aCompCor",
    "Retained": true,
    "SingularValue": 111.3900366235,
    "VarianceExplained": 0.002425346
  },
  "w_comp_cor_11": {
    "CumulativeVarianceExplained": 0.0576733953,
    "Mask": "WM",
    "Method": "aCompCor",
    "Retained": true,
    "SingularValue": 127.6979744509,
    "VarianceExplained": 0.0031874914
  },
  "w_comp_cor_110": {
    "CumulativeVarianceExplained": 0.3220446943,
    "Mask": "WM",
    "Method": "aCompCor",
    "Retained": true,
    "SingularValue": 111.3574669523,
    "VarianceExplained": 0.0024239279
  },
  "w_comp_cor_111": {
    "CumulativeVarianceExplained": 0.3244585343,
    "Mask": "WM",
    "Method": "aCompCor",
    "Retained": true,
    "SingularValue": 111.125502971,
    "VarianceExplained": 0.00241384
  },
  "w_comp_cor_112": {
    "CumulativeVarianceExplained": 0.3268674968,
    "Mask": "WM",
    "Method": "aCompCor",
    "Retained": true,
    "SingularValue": 111.0131716971,
    "VarianceExplained": 0.0024089625
  },
  "w_comp_cor_113": {
    "CumulativeVarianceExplained": 0.3292704129,
    "Mask": "WM",
    "Method": "aCompCor",
    "Retained": true,
    "SingularValue": 110.8737663229,
    "VarianceExplained": 0.0024029161
  },
  "w_comp_cor_114": {
    "CumulativeVarianceExplained": 0.3316718553,
    "Mask": "WM",
    "Method": "aCompCor",
    "Retained": true,
    "SingularValue": 110.8397627049,
    "VarianceExplained": 0.0024014425
  },
  "w_comp_cor_115": {
    "CumulativeVarianceExplained": 0.3340692522,
    "Mask": "WM",
    "Method": "aCompCor",
    "Retained": true,
    "SingularValue": 110.7463600835,
    "VarianceExplained": 0.0023973969
  },
  "w_comp_cor_116": {
    "CumulativeVarianceExplained": 0.3364621767,
    "Mask": "WM",
    "Method": "aCompCor",
    "Retained": true,
    "SingularValue": 110.6430137077,
    "VarianceExplained": 0.0023929245
  },
  "w_comp_cor_117": {
    "CumulativeVarianceExplained": 0.3388533132,
    "Mask": "WM",
    "Method": "aCompCor",
    "Retained": true,
    "SingularValue": 110.6016685646,
    "VarianceExplained": 0.0023911365
  },
  "w_comp_cor_118": {
    "CumulativeVarianceExplained": 0.3412376367,
    "Mask": "WM",
    "Method": "aCompCor",
    "Retained": true,
    "SingularValue": 110.4439899599,
    "VarianceExplained": 0.0023843235
  },
  "w_comp_cor_119": {
    "CumulativeVarianceExplained": 0.3436168,
    "Mask": "WM",
    "Method": "aCompCor",
    "Retained": true,
    "SingularValue": 110.3244108543,
    "VarianceExplained": 0.0023791633
  },
  "w_comp_cor_12": {
    "CumulativeVarianceExplained": 0.0608187185,
    "Mask": "WM",
    "Method": "aCompCor",
    "Retained": true,
    "SingularValue": 126.8504852964,
    "VarianceExplained": 0.0031453232
  },
  "w_comp_cor_120": {
    "CumulativeVarianceExplained": 0.3459923347,
    "Mask": "WM",
    "Method": "aCompCor",
    "Retained": true,
    "SingularValue": 110.2402491573,
    "VarianceExplained": 0.0023755347
  },
  "w_comp_cor_121": {
    "CumulativeVarianceExplained": 0.3483633444,
    "Mask": "WM",
    "Method": "aCompCor",
    "Retained": true,
    "SingularValue": 110.1352030395,
    "VarianceExplained": 0.0023710097
  },
  "w_comp_cor_122": {
    "CumulativeVarianceExplained": 0.3507330392,
    "Mask": "WM",
    "Method": "aCompCor",
    "Retained": true,
    "SingularValue": 110.1046624581,
    "VarianceExplained": 0.0023696949
  },
  "w_comp_cor_123": {
    "CumulativeVarianceExplained": 0.3531007045,
    "Mask": "WM",
    "Method": "aCompCor",
    "Retained": true,
    "SingularValue": 110.05750116,
    "VarianceExplained": 0.0023676653
  },
  "w_comp_cor_124": {
    "CumulativeVarianceExplained": 0.3554660838,
    "Mask": "WM",
    "Method": "aCompCor",
    "Retained": true,
    "SingularValue": 110.0043587037,
    "VarianceExplained": 0.0023653793
  },
  "w_comp_cor_125": {
    "CumulativeVarianceExplained": 0.3578242602,
    "Mask": "WM",
    "Method": "aCompCor",
    "Retained": true,
    "SingularValue": 109.8367400668,
    "VarianceExplained": 0.0023581763
  },
  "w_comp_cor_126": {
    "CumulativeVarianceExplained": 0.3601801414,
    "Mask": "WM",
    "Method": "aCompCor",
    "Retained": true,
    "SingularValue": 109.7832763251,
    "VarianceExplained": 0.0023558812
  },
  "w_comp_cor_127": {
    "CumulativeVarianceExplained": 0.3625277237,
    "Mask": "WM",
    "Method": "aCompCor",
    "Retained": true,
    "SingularValue": 109.5897428838,
    "VarianceExplained": 0.0023475823
  },
  "w_comp_cor_128": {
    "CumulativeVarianceExplained": 0.3648743173,
    "Mask": "WM",
    "Method": "aCompCor",
    "Retained": true,
    "SingularValue": 109.5666639867,
    "VarianceExplained": 0.0023465936
  },
  "w_comp_cor_129": {
    "CumulativeVarianceExplained": 0.3672170618,
    "Mask": "WM",
    "Method": "aCompCor",
    "Retained": true,
    "SingularValue": 109.4767665964,
    "VarianceExplained": 0.0023427445
  },
  "w_comp_cor_13": {
    "CumulativeVarianceExplained": 0.0639485044,
    "Mask": "WM",
    "Method": "aCompCor",
    "Retained": true,
    "SingularValue": 126.5367890996,
    "VarianceExplained": 0.0031297859
  },
  "w_comp_cor_130": {
    "CumulativeVarianceExplained": 0.3695578693,
    "Mask": "WM",
    "Method": "aCompCor",
    "Retained": true,
    "SingularValue": 109.4314976565,
    "VarianceExplained": 0.0023408075
  },
  "w_comp_cor_131": {
    "CumulativeVarianceExplained": 0.3718927446,
    "Mask": "WM",
    "Method": "aCompCor",
    "Retained": true,
    "SingularValue": 109.2927462412,
    "VarianceExplained": 0.0023348753
  },
  "w_comp_cor_132": {
    "CumulativeVarianceExplained": 0.3742250435,
    "Mask": "WM",
    "Method": "aCompCor",
    "Retained": true,
    "SingularValue": 109.2324313965,
    "VarianceExplained": 0.0023322989
  },
  "w_comp_cor_133": {
    "CumulativeVarianceExplained": 0.3765518528,
    "Mask": "WM",
    "Method": "aCompCor",
    "Retained": true,
    "SingularValue": 109.1038042029,
    "VarianceExplained": 0.0023268093
  },
  "w_comp_cor_134": {
    "CumulativeVarianceExplained": 0.3788726381,
    "Mask": "WM",
    "Method": "aCompCor",
    "Retained": true,
    "SingularValue": 108.9624794185,
    "VarianceExplained": 0.0023207853
  },
  "w_comp_cor_135": {
    "CumulativeVarianceExplained": 0.3811931314,
    "Mask": "WM",
    "Method": "aCompCor",
    "Retained": true,
    "SingularValue": 108.9556250892,
    "VarianceExplained": 0.0023204933
  },
  "w_comp_cor_136": {
    "CumulativeVarianceExplained": 0.3835111616,
    "Mask": "WM",
    "Method": "aCompCor",
    "Retained": true,
    "SingularValue": 108.8977814182,
    "VarianceExplained": 0.0023180301
  },
  "w_comp_cor_137": {
    "CumulativeVarianceExplained": 0.3858268396,
    "Mask": "WM",
    "Method": "aCompCor",
    "Retained": true,
    "SingularValue": 108.8425189191,
    "VarianceExplained": 0.002315678
  },
  "w_comp_cor_138": {
    "CumulativeVarianceExplained": 0.3881404326,
    "Mask": "WM",
    "Method": "aCompCor",
    "Retained": true,
    "SingularValue": 108.7935072506,
    "VarianceExplained": 0.002313593
  },
  "w_comp_cor_139": {
    "CumulativeVarianceExplained": 0.3904514298,
    "Mask": "WM",
    "Method": "aCompCor",
    "Retained": true,
    "SingularValue": 108.7324571903,
    "VarianceExplained": 0.0023109972
  },
  "w_comp_cor_14": {
    "CumulativeVarianceExplained": 0.0669935575,
    "Mask": "WM",
    "Method": "aCompCor",
    "Retained": true,
    "SingularValue": 124.8121701119,
    "VarianceExplained": 0.0030450532
  },
  "w_comp_cor_140": {
    "CumulativeVarianceExplained": 0.3927582039,
    "Mask": "WM",
    "Method": "aCompCor",
    "Retained": true,
    "SingularValue": 108.6330646297,
    "VarianceExplained": 0.0023067741
  },
  "w_comp_cor_141": {
    "CumulativeVarianceExplained": 0.395061035,
    "Mask": "WM",
    "Method": "aCompCor",
    "Retained": true,
    "SingularValue": 108.5401789764,
    "VarianceExplained": 0.002302831
  },
  "w_comp_cor_142": {
    "CumulativeVarianceExplained": 0.3973573742,
    "Mask": "WM",
    "Method": "aCompCor",
    "Retained": true,
    "SingularValue": 108.3870816947,
    "VarianceExplained": 0.0022963393
  },
  "w_comp_cor_143": {
    "CumulativeVarianceExplained": 0.3996490044,
    "Mask": "WM",
    "Method": "aCompCor",
    "Retained": true,
    "SingularValue": 108.2758882559,
    "VarianceExplained": 0.0022916301
  },
  "w_comp_cor_144": {
    "CumulativeVarianceExplained": 0.4019372725,
    "Mask": "WM",
    "Method": "aCompCor",
    "Retained": true,
    "SingularValue": 108.1964362496,
    "VarianceExplained": 0.0022882682
  },
  "w_comp_cor_145": {
    "CumulativeVarianceExplained": 0.4042242959,
    "Mask": "WM",
    "Method": "aCompCor",
    "Retained": true,
    "SingularValue": 108.1670031661,
    "VarianceExplained": 0.0022870234
  },
  "w_comp_cor_146": {
    "CumulativeVarianceExplained": 0.4065058109,
    "Mask": "WM",
    "Method": "aCompCor",
    "Retained": true,
    "SingularValue": 108.036661389,
    "VarianceExplained": 0.002281515
  },
  "w_comp_cor_147": {
    "CumulativeVarianceExplained": 0.4087858828,
    "Mask": "WM",
    "Method": "aCompCor",
    "Retained": true,
    "SingularValue": 108.0024896087,
    "VarianceExplained": 0.0022800719
  },
  "w_comp_cor_148": {
    "CumulativeVarianceExplained": 0.4110601769,
    "Mask": "WM",
    "Method": "aCompCor",
    "Retained": true,
    "SingularValue": 107.865562433,
    "VarianceExplained": 0.0022742941
  },
  "w_comp_cor_149": {
    "CumulativeVarianceExplained": 0.4133337872,
    "Mask": "WM",
    "Method": "aCompCor",
    "Retained": true,
    "SingularValue": 107.8493443352,
    "VarianceExplained": 0.0022736103
  },
  "w_comp_cor_15": {
    "CumulativeVarianceExplained": 0.0700311513,
    "Mask": "WM",
    "Method": "aCompCor",
    "Retained": true,
    "SingularValue": 124.6592029422,
    "VarianceExplained": 0.0030375938
  },
  "w_comp_cor_150": {
    "CumulativeVarianceExplained": 0.4156036769,
    "Mask": "WM",
    "Method": "aCompCor",
    "Retained": true,
    "SingularValue": 107.7610643345,
    "VarianceExplained": 0.0022698897
  },
  "w_comp_cor_151": {
    "CumulativeVarianceExplained": 0.4178724281,
    "Mask": "WM",
    "Method": "aCompCor",
    "Retained": true,
    "SingularValue": 107.7340362715,
    "VarianceExplained": 0.0022687512
  },
  "w_comp_cor_152": {
    "CumulativeVarianceExplained": 0.4201364004,
    "Mask": "WM",
    "Method": "aCompCor",
    "Retained": true,
    "SingularValue": 107.6205106895,
    "VarianceExplained": 0.0022639723
  },
  "w_comp_cor_153": {
    "CumulativeVarianceExplained": 0.4223968897,
    "Mask": "WM",
    "Method": "aCompCor",
    "Retained": true,
    "SingularValue": 107.5376961528,
    "VarianceExplained": 0.0022604894
  },
  "w_comp_cor_154": {
    "CumulativeVarianceExplained": 0.4246556714,
    "Mask": "WM",
    "Method": "aCompCor",
    "Retained": true,
    "SingularValue": 107.4970686771,
    "VarianceExplained": 0.0022587817
  },
  "w_comp_cor_155": {
    "CumulativeVarianceExplained": 0.4269107537,
    "Mask": "WM",
    "Method": "aCompCor",
    "Retained": true,
    "SingularValue": 107.409006,
    "VarianceExplained": 0.0022550823
  },
  "w_comp_cor_156": {
    "CumulativeVarianceExplained": 0.4291642469,
    "Mask": "WM",
    "Method": "aCompCor",
    "Retained": true,
    "SingularValue": 107.3711532456,
    "VarianceExplained": 0.0022534932
  },
  "w_comp_cor_157": {
    "CumulativeVarianceExplained": 0.4314126694,
    "Mask": "WM",
    "Method": "aCompCor",
    "Retained": true,
    "SingularValue": 107.2502849321,
    "VarianceExplained": 0.0022484225
  },
  "w_comp_cor_158": {
    "CumulativeVarianceExplained": 0.4336584362,
    "Mask": "WM",
    "Method": "aCompCor",
    "Retained": true,
    "SingularValue": 107.1869283947,
    "VarianceExplained": 0.0022457668
  },
  "w_comp_cor_159": {
    "CumulativeVarianceExplained": 0.4359022536,
    "Mask": "WM",
    "Method": "aCompCor",
    "Retained": true,
    "SingularValue": 107.1403964839,
    "VarianceExplained": 0.0022438174
  },
  "w_comp_cor_16": {
    "CumulativeVarianceExplained": 0.0730576672,
    "Mask": "WM",
    "Method": "aCompCor",
    "Retained": true,
    "SingularValue": 124.4316823336,
    "VarianceExplained": 0.0030265159
  },
  "w_comp_cor_160": {
    "CumulativeVarianceExplained": 0.4381422192,
    "Mask": "WM",
    "Method": "aCompCor",
    "Retained": true,
    "SingularValue": 107.0483977507,
    "VarianceExplained": 0.0022399656
  },
  "w_comp_cor_161": {
    "CumulativeVarianceExplained": 0.4403728629,
    "Mask": "WM",
    "Method": "aCompCor",
    "Retained": true,
    "SingularValue": 106.8254179881,
    "VarianceExplained": 0.0022306437
  },
  "w_comp_cor_162": {
    "CumulativeVarianceExplained": 0.4426028801,
    "Mask": "WM",
    "Method": "aCompCor",
    "Retained": true,
    "SingularValue": 106.8104149217,
    "VarianceExplained": 0.0022300172
  },
  "w_comp_cor_163": {
    "CumulativeVarianceExplained": 0.4448325434,
    "Mask": "WM",
    "Method": "aCompCor",
    "Retained": true,
    "SingularValue": 106.8019393927,
    "VarianceExplained": 0.0022296633
  },
  "w_comp_cor_164": {
    "CumulativeVarianceExplained": 0.4470550946,
    "Mask": "WM",
    "Method": "aCompCor",
    "Retained": true,
    "SingularValue": 106.6314649207,
    "VarianceExplained": 0.0022225511
  },
  "w_comp_cor_165": {
    "CumulativeVarianceExplained": 0.4492743611,
    "Mask": "WM",
    "Method": "aCompCor",
    "Retained": true,
    "SingularValue": 106.5526433963,
    "VarianceExplained": 0.0022192665
  },
  "w_comp_cor_166": {
    "CumulativeVarianceExplained": 0.4514918035,
    "Mask": "WM",
    "Method": "aCompCor",
    "Retained": true,
    "SingularValue": 106.5088428762,
    "VarianceExplained": 0.0022174424
  },
  "w_comp_cor_167": {
    "CumulativeVarianceExplained": 0.453702052,
    "Mask": "WM",
    "Method": "aCompCor",
    "Retained": true,
    "SingularValue": 106.3359342975,
    "VarianceExplained": 0.0022102485
  },
  "w_comp_cor_168": {
    "CumulativeVarianceExplained": 0.4559107994,
    "Mask": "WM",
    "Method": "aCompCor",
    "Retained": true,
    "SingularValue": 106.2998168565,
    "VarianceExplained": 0.0022087474
  },
  "w_comp_cor_169": {
    "CumulativeVarianceExplained": 0.4581157335,
    "Mask": "WM",
    "Method": "aCompCor",
    "Retained": true,
    "SingularValue": 106.2080171818,
    "VarianceExplained": 0.0022049341
  },
  "w_comp_cor_17": {
    "CumulativeVarianceExplained": 0.0760575332,
    "Mask": "WM",
    "Method": "aCompCor",
    "Retained": true,
    "SingularValue": 123.8826317263,
    "VarianceExplained": 0.002999866
  },
  "w_comp_cor_170": {
    "CumulativeVarianceExplained": 0.4603172439,
    "Mask": "WM",
    "Method": "aCompCor",
    "Retained": true,
    "SingularValue": 106.1255298789,
    "VarianceExplained": 0.0022015105
  },
  "w_comp_cor_171": {
    "CumulativeVarianceExplained": 0.4625182169,
    "Mask": "WM",
    "Method": "aCompCor",
    "Retained": true,
    "SingularValue": 106.1125744093,
    "VarianceExplained": 0.002200973
  },
  "w_comp_cor_172": {
    "CumulativeVarianceExplained": 0.4647115578,
    "Mask": "WM",
    "Method": "aCompCor",
    "Retained": true,
    "SingularValue": 105.9284379632,
    "VarianceExplained": 0.0021933409
  },
  "w_comp_cor_173": {
    "CumulativeVarianceExplained": 0.4669032912,
    "Mask": "WM",
    "Method": "aCompCor",
    "Retained": true,
    "SingularValue": 105.889610613,
    "VarianceExplained": 0.0021917333
  },
  "w_comp_cor_174": {
    "CumulativeVarianceExplained": 0.4690923531,
    "Mask": "WM",
    "Method": "aCompCor",
    "Retained": true,
    "SingularValue": 105.825059107,
    "VarianceExplained": 0.0021890619
  },
  "w_comp_cor_175": {
    "CumulativeVarianceExplained": 0.471277972,
    "Mask": "WM",
    "Method": "aCompCor",
    "Retained": true,
    "SingularValue": 105.7418022304,
    "VarianceExplained": 0.0021856188
  },
  "w_comp_cor_176": {
    "CumulativeVarianceExplained": 0.4734612324,
    "Mask": "WM",
    "Method": "aCompCor",
    "Retained": true,
    "SingularValue": 105.6847359297,
    "VarianceExplained": 0.0021832604
  },
  "w_comp_cor_177": {
    "CumulativeVarianceExplained": 0.4756389021,
    "Mask": "WM",
    "Method": "aCompCor",
    "Retained": true,
    "SingularValue": 105.5493346099,
    "VarianceExplained": 0.0021776697
  },
  "w_comp_cor_178": {
    "CumulativeVarianceExplained": 0.4778132298,
    "Mask": "WM",
    "Method": "aCompCor",
    "Retained": true,
    "SingularValue": 105.4683121155,
    "VarianceExplained": 0.0021743277
  },
  "w_comp_cor_179": {
    "CumulativeVarianceExplained": 0.4799842867,
    "Mask": "WM",
    "Method": "aCompCor",
    "Retained": true,
    "SingularValue": 105.3889548694,
    "VarianceExplained": 0.0021710569
  },
  "w_comp_cor_18": {
    "CumulativeVarianceExplained": 0.0790305145,
    "Mask": "WM",
    "Method": "aCompCor",
    "Retained": true,
    "SingularValue": 123.3262671437,
    "VarianceExplained": 0.0029729813
  },
  "w_comp_cor_180": {
    "CumulativeVarianceExplained": 0.4821503577,
    "Mask": "WM",
    "Method": "aCompCor",
    "Retained": true,
    "SingularValue": 105.2678703518,
    "VarianceExplained": 0.002166071
  },
  "w_comp_cor_181": {
    "CumulativeVarianceExplained": 0.4843141401,
    "Mask": "WM",
    "Method": "aCompCor",
    "Retained": true,
    "SingularValue": 105.2122447451,
    "VarianceExplained": 0.0021637824
  },
  "w_comp_cor_182": {
    "CumulativeVarianceExplained": 0.4864755013,
    "Mask": "WM",
    "Method": "aCompCor",
    "Retained": true,
    "SingularValue": 105.1533654143,
    "VarianceExplained": 0.0021613613
  },
  "w_comp_cor_183": {
    "CumulativeVarianceExplained": 0.488631521,
    "Mask": "WM",
    "Method": "aCompCor",
    "Retained": true,
    "SingularValue": 105.0233471107,
    "VarianceExplained": 0.0021560197
  },
  "w_comp_cor_184": {
    "CumulativeVarianceExplained": 0.4907841577,
    "Mask": "WM",
    "Method": "aCompCor",
    "Retained": true,
    "SingularValue": 104.9409200278,
    "VarianceExplained": 0.0021526367
  },
  "w_comp_cor_185": {
    "CumulativeVarianceExplained": 0.4929363392,
    "Mask": "WM",
    "Method": "aCompCor",
    "Retained": true,
    "SingularValue": 104.9298229477,
    "VarianceExplained": 0.0021521815
  },
  "w_comp_cor_186": {
    "CumulativeVarianceExplained": 0.4950857036,
    "Mask": "WM",
    "Method": "aCompCor",
    "Retained": true,
    "SingularValue": 104.8611272342,
    "VarianceExplained": 0.0021493644
  },
  "w_comp_cor_187": {
    "CumulativeVarianceExplained": 0.4972314903,
    "Mask": "WM",
    "Method": "aCompCor",
    "Retained": true,
    "SingularValue": 104.7738177089,
    "VarianceExplained": 0.0021457867
  },
  "w_comp_cor_188": {
    "CumulativeVarianceExplained": 0.4993747094,
    "Mask": "WM",
    "Method": "aCompCor",
    "Retained": true,
    "SingularValue": 104.7111138598,
    "VarianceExplained": 0.0021432191
  },
  "w_comp_cor_189": {
    "CumulativeVarianceExplained": 0.501515226,
    "Mask": "WM",
    "Method": "aCompCor",
    "Retained": true,
    "SingularValue": 104.6450756181,
    "VarianceExplained": 0.0021405166
  },
  "w_comp_cor_19": {
    "CumulativeVarianceExplained": 0.0819989886,
    "Mask": "WM",
    "Method": "aCompCor",
    "Retained": true,
    "SingularValue": 123.2327458949,
    "VarianceExplained": 0.0029684741
  },
  "w_comp_cor_20": {
    "CumulativeVarianceExplained": 0.0849382242,
    "Mask": "WM",
    "Method": "aCompCor",
    "Retained": true,
    "SingularValue": 122.6243443202,
    "VarianceExplained": 0.0029392356
  },
  "w_comp_cor_21": {
    "CumulativeVarianceExplained": 0.0878691023,
    "Mask": "WM",
    "Method": "aCompCor",
    "Retained": true,
    "SingularValue": 122.4498818032,
    "VarianceExplained": 0.0029308781
  },
  "w_comp_cor_22": {
    "CumulativeVarianceExplained": 0.0907954636,
    "Mask": "WM",
    "Method": "aCompCor",
    "Retained": true,
    "SingularValue": 122.3554929351,
    "VarianceExplained": 0.0029263613
  },
  "w_comp_cor_23": {
    "CumulativeVarianceExplained": 0.0937118595,
    "Mask": "WM",
    "Method": "aCompCor",
    "Retained": true,
    "SingularValue": 122.14697894,
    "VarianceExplained": 0.0029163958
  },
  "w_comp_cor_24": {
    "CumulativeVarianceExplained": 0.0966060449,
    "Mask": "WM",
    "Method": "aCompCor",
    "Retained": true,
    "SingularValue": 121.6809714581,
    "VarianceExplained": 0.0028941854
  },
  "w_comp_cor_25": {
    "CumulativeVarianceExplained": 0.0994908303,
    "Mask": "WM",
    "Method": "aCompCor",
    "Retained": true,
    "SingularValue": 121.4832090953,
    "VarianceExplained": 0.0028847855
  },
  "w_comp_cor_26": {
    "CumulativeVarianceExplained": 0.1023669012,
    "Mask": "WM",
    "Method": "aCompCor",
    "Retained": true,
    "SingularValue": 121.2995769753,
    "VarianceExplained": 0.0028760709
  },
  "w_comp_cor_27": {
    "CumulativeVarianceExplained": 0.1052271553,
    "Mask": "WM",
    "Method": "aCompCor",
    "Retained": true,
    "SingularValue": 120.9655780401,
    "VarianceExplained": 0.0028602541
  },
  "w_comp_cor_28": {
    "CumulativeVarianceExplained": 0.1080817722,
    "Mask": "WM",
    "Method": "aCompCor",
    "Retained": true,
    "SingularValue": 120.8463152124,
    "VarianceExplained": 0.0028546169
  },
  "w_comp_cor_29": {
    "CumulativeVarianceExplained": 0.1109293684,
    "Mask": "WM",
    "Method": "aCompCor",
    "Retained": true,
    "SingularValue": 120.6976173523,
    "VarianceExplained": 0.0028475962
  },
  "w_comp_cor_30": {
    "CumulativeVarianceExplained": 0.1137658113,
    "Mask": "WM",
    "Method": "aCompCor",
    "Retained": true,
    "SingularValue": 120.4610139914,
    "VarianceExplained": 0.0028364429
  },
  "w_comp_cor_31": {
    "CumulativeVarianceExplained": 0.1165912496,
    "Mask": "WM",
    "Method": "aCompCor",
    "Retained": true,
    "SingularValue": 120.227110242,
    "VarianceExplained": 0.0028254383
  },
  "w_comp_cor_32": {
    "CumulativeVarianceExplained": 0.1194040943,
    "Mask": "WM",
    "Method": "aCompCor",
    "Retained": true,
    "SingularValue": 119.9588718246,
    "VarianceExplained": 0.0028128447
  },
  "w_comp_cor_33": {
    "CumulativeVarianceExplained": 0.1222115061,
    "Mask": "WM",
    "Method": "aCompCor",
    "Retained": true,
    "SingularValue": 119.8429684921,
    "VarianceExplained": 0.0028074118
  },
  "w_comp_cor_34": {
    "CumulativeVarianceExplained": 0.1250153439,
    "Mask": "WM",
    "Method": "aCompCor",
    "Retained": true,
    "SingularValue": 119.7666607478,
    "VarianceExplained": 0.0028038378
  },
  "w_comp_cor_35": {
    "CumulativeVarianceExplained": 0.1278121909,
    "Mask": "WM",
    "Method": "aCompCor",
    "Retained": true,
    "SingularValue": 119.6172588452,
    "VarianceExplained": 0.0027968469
  },
  "w_comp_cor_36": {
    "CumulativeVarianceExplained": 0.1306042449,
    "Mask": "WM",
    "Method": "aCompCor",
    "Retained": true,
    "SingularValue": 119.5147211909,
    "VarianceExplained": 0.002792054
  },
  "w_comp_cor_37": {
    "CumulativeVarianceExplained": 0.1333940301,
    "Mask": "WM",
    "Method": "aCompCor",
    "Retained": true,
    "SingularValue": 119.4661528897,
    "VarianceExplained": 0.0027897852
  },
  "w_comp_cor_38": {
    "CumulativeVarianceExplained": 0.1361777923,
    "Mask": "WM",
    "Method": "aCompCor",
    "Retained": true,
    "SingularValue": 119.3371222477,
    "VarianceExplained": 0.0027837622
  },
  "w_comp_cor_39": {
    "CumulativeVarianceExplained": 0.1389567688,
    "Mask": "WM",
    "Method": "aCompCor",
    "Retained": true,
    "SingularValue": 119.2344997818,
    "VarianceExplained": 0.0027789765
  },
  "w_comp_cor_40": {
    "CumulativeVarianceExplained": 0.1417262764,
    "Mask": "WM",
    "Method": "aCompCor",
    "Retained": true,
    "SingularValue": 119.0311902711,
    "VarianceExplained": 0.0027695076
  },
  "w_comp_cor_41": {
    "CumulativeVarianceExplained": 0.1444809427,
    "Mask": "WM",
    "Method": "aCompCor",
    "Retained": true,
    "SingularValue": 118.7118281975,
    "VarianceExplained": 0.0027546663
  },
  "w_comp_cor_42": {
    "CumulativeVarianceExplained": 0.1472332609,
    "Mask": "WM",
    "Method": "aCompCor",
    "Retained": true,
    "SingularValue": 118.661222199,
    "VarianceExplained": 0.0027523182
  },
  "w_comp_cor_43": {
    "CumulativeVarianceExplained": 0.1499806034,
    "Mask": "WM",
    "Method": "aCompCor",
    "Retained": true,
    "SingularValue": 118.5539148993,
    "VarianceExplained": 0.0027473425
  },
  "w_comp_cor_44": {
    "CumulativeVarianceExplained": 0.152720177,
    "Mask": "WM",
    "Method": "aCompCor",
    "Retained": true,
    "SingularValue": 118.3861716369,
    "VarianceExplained": 0.0027395735
  },
  "w_comp_cor_45": {
    "CumulativeVarianceExplained": 0.1554534449,
    "Mask": "WM",
    "Method": "aCompCor",
    "Retained": true,
    "SingularValue": 118.2498504448,
    "VarianceExplained": 0.002733268
  },
  "w_comp_cor_46": {
    "CumulativeVarianceExplained": 0.1581842487,
    "Mask": "WM",
    "Method": "aCompCor",
    "Retained": true,
    "SingularValue": 118.1965339966,
    "VarianceExplained": 0.0027308038
  },
  "w_comp_cor_47": {
    "CumulativeVarianceExplained": 0.1609065014,
    "Mask": "WM",
    "Method": "aCompCor",
    "Retained": true,
    "SingularValue": 118.011332027,
    "VarianceExplained": 0.0027222527
  },
  "w_comp_cor_48": {
    "CumulativeVarianceExplained": 0.1636162649,
    "Mask": "WM",
    "Method": "aCompCor",
    "Retained": true,
    "SingularValue": 117.7403145208,
    "VarianceExplained": 0.0027097635
  },
  "w_comp_cor_49": {
    "CumulativeVarianceExplained": 0.1663227817,
    "Mask": "WM",
    "Method": "aCompCor",
    "Retained": true,
    "SingularValue": 117.6697585276,
    "VarianceExplained": 0.0027065168
  },
  "w_comp_cor_50": {
    "CumulativeVarianceExplained": 0.1690233503,
    "Mask": "WM",
    "Method": "aCompCor",
    "Retained": true,
    "SingularValue": 117.5403822018,
    "VarianceExplained": 0.0027005686
  },
  "w_comp_cor_51": {
    "CumulativeVarianceExplained": 0.1717204652,
    "Mask": "WM",
    "Method": "aCompCor",
    "Retained": true,
    "SingularValue": 117.4651999234,
    "VarianceExplained": 0.0026971149
  },
  "w_comp_cor_52": {
    "CumulativeVarianceExplained": 0.1744115133,
    "Mask": "WM",
    "Method": "aCompCor",
    "Retained": true,
    "SingularValue": 117.3330136885,
    "VarianceExplained": 0.0026910481
  },
  "w_comp_cor_53": {
    "CumulativeVarianceExplained": 0.1771009258,
    "Mask": "WM",
    "Method": "aCompCor",
    "Retained": true,
    "SingularValue": 117.2973510711,
    "VarianceExplained": 0.0026894125
  },
  "w_comp_cor_54": {
    "CumulativeVarianceExplained": 0.1797849447,
    "Mask": "WM",
    "Method": "aCompCor",
    "Retained": true,
    "SingularValue": 117.1796735066,
    "VarianceExplained": 0.0026840189
  },
  "w_comp_cor_55": {
    "CumulativeVarianceExplained": 0.1824641302,
    "Mask": "WM",
    "Method": "aCompCor",
    "Retained": true,
    "SingularValue": 117.0741157004,
    "VarianceExplained": 0.0026791855
  },
  "w_comp_cor_56": {
    "CumulativeVarianceExplained": 0.1851359005,
    "Mask": "WM",
    "Method": "aCompCor",
    "Retained": true,
    "SingularValue": 116.9119895227,
    "VarianceExplained": 0.0026717703
  },
  "w_comp_cor_57": {
    "CumulativeVarianceExplained": 0.1877977489,
    "Mask": "WM",
    "Method": "aCompCor",
    "Retained": true,
    "SingularValue": 116.6947070376,
    "VarianceExplained": 0.0026618484
  },
  "w_comp_cor_58": {
    "CumulativeVarianceExplained": 0.1904554782,
    "Mask": "WM",
    "Method": "aCompCor",
    "Retained": true,
    "SingularValue": 116.6043792428,
    "VarianceExplained": 0.0026577292
  },
  "w_comp_cor_59": {
    "CumulativeVarianceExplained": 0.1931060967,
    "Mask": "WM",
    "Method": "aCompCor",
    "Retained": true,
    "SingularValue": 116.4482894876,
    "VarianceExplained": 0.0026506186
  },
  "w_comp_cor_60": {
    "CumulativeVarianceExplained": 0.1957535694,
    "Mask": "WM",
    "Method": "aCompCor",
    "Retained": true,
    "SingularValue": 116.379164958,
    "VarianceExplained": 0.0026474727
  },
  "w_comp_cor_61": {
    "CumulativeVarianceExplained": 0.1983985387,
    "Mask": "WM",
    "Method": "aCompCor",
    "Retained": true,
    "SingularValue": 116.3241312934,
    "VarianceExplained": 0.0026449694
  },
  "w_comp_cor_62": {
    "CumulativeVarianceExplained": 0.2010347269,
    "Mask": "WM",
    "Method": "aCompCor",
    "Retained": true,
    "SingularValue": 116.1308757935,
    "VarianceExplained": 0.0026361882
  },
  "w_comp_cor_63": {
    "CumulativeVarianceExplained": 0.2036673749,
    "Mask": "WM",
    "Method": "aCompCor",
    "Retained": true,
    "SingularValue": 116.0528704292,
    "VarianceExplained": 0.0026326479
  },
  "w_comp_cor_64": {
    "CumulativeVarianceExplained": 0.2062980636,
    "Mask": "WM",
    "Method": "aCompCor",
    "Retained": true,
    "SingularValue": 116.0096803915,
    "VarianceExplained": 0.0026306888
  },
  "w_comp_cor_65": {
    "CumulativeVarianceExplained": 0.2089165478,
    "Mask": "WM",
    "Method": "aCompCor",
    "Retained": true,
    "SingularValue": 115.7402640931,
    "VarianceExplained": 0.0026184841
  },
  "w_comp_cor_66": {
    "CumulativeVarianceExplained": 0.2115335261,
    "Mask": "WM",
    "Method": "aCompCor",
    "Retained": true,
    "SingularValue": 115.7069806771,
    "VarianceExplained": 0.0026169784
  },
  "w_comp_cor_67": {
    "CumulativeVarianceExplained": 0.2141448674,
    "Mask": "WM",
    "Method": "aCompCor",
    "Retained": true,
    "SingularValue": 115.582294068,
    "VarianceExplained": 0.0026113413
  },
  "w_comp_cor_68": {
    "CumulativeVarianceExplained": 0.2167497724,
    "Mask": "WM",
    "Method": "aCompCor",
    "Retained": true,
    "SingularValue": 115.4397676233,
    "VarianceExplained": 0.002604905
  },
  "w_comp_cor_69": {
    "CumulativeVarianceExplained": 0.2193461826,
    "Mask": "WM",
    "Method": "aCompCor",
    "Retained": true,
    "SingularValue": 115.2513836475,
    "VarianceExplained": 0.0025964102
  },
  "w_comp_cor_70": {
    "CumulativeVarianceExplained": 0.2219392896,
    "Mask": "WM",
    "Method": "aCompCor",
    "Retained": true,
    "SingularValue": 115.1780464983,
    "VarianceExplained": 0.0025931069
  },
  "w_comp_cor_71": {
    "CumulativeVarianceExplained": 0.224529857,
    "Mask": "WM",
    "Method": "aCompCor",
    "Retained": true,
    "SingularValue": 115.1216350491,
    "VarianceExplained": 0.0025905675
  },
  "w_comp_cor_72": {
    "CumulativeVarianceExplained": 0.2271129925,
    "Mask": "WM",
    "Method": "aCompCor",
    "Retained": true,
    "SingularValue": 114.9563816193,
    "VarianceExplained": 0.0025831355
  },
  "w_comp_cor_73": {
    "CumulativeVarianceExplained": 0.2296932332,
    "Mask": "WM",
    "Method": "aCompCor",
    "Retained": true,
    "SingularValue": 114.8919511715,
    "VarianceExplained": 0.0025802407
  },
  "w_comp_cor_74": {
    "CumulativeVarianceExplained": 0.2322700806,
    "Mask": "WM",
    "Method": "aCompCor",
    "Retained": true,
    "SingularValue": 114.8163789251,
    "VarianceExplained": 0.0025768474
  },
  "w_comp_cor_75": {
    "CumulativeVarianceExplained": 0.2348445255,
    "Mask": "WM",
    "Method": "aCompCor",
    "Retained": true,
    "SingularValue": 114.762841932,
    "VarianceExplained": 0.0025744449
  },
  "w_comp_cor_76": {
    "CumulativeVarianceExplained": 0.2374117295,
    "Mask": "WM",
    "Method": "aCompCor",
    "Retained": true,
    "SingularValue": 114.6013378127,
    "VarianceExplained": 0.002567204
  },
  "w_comp_cor_77": {
    "CumulativeVarianceExplained": 0.2399770602,
    "Mask": "WM",
    "Method": "aCompCor",
    "Retained": true,
    "SingularValue": 114.5595188379,
    "VarianceExplained": 0.0025653308
  },
  "w_comp_cor_78": {
    "CumulativeVarianceExplained": 0.2425401918,
    "Mask": "WM",
    "Method": "aCompCor",
    "Retained": true,
    "SingularValue": 114.5104037962,
    "VarianceExplained": 0.0025631316
  },
  "w_comp_cor_79": {
    "CumulativeVarianceExplained": 0.2450913046,
    "Mask": "WM",
    "Method": "aCompCor",
    "Retained": true,
    "SingularValue": 114.241613046,
    "VarianceExplained": 0.0025511128
  },
  "w_comp_cor_80": {
    "CumulativeVarianceExplained": 0.2476415456,
    "Mask": "WM",
    "Method": "aCompCor",
    "Retained": true,
    "SingularValue": 114.2220904032,
    "VarianceExplained": 0.002550241
  },
  "w_comp_cor_81": {
    "CumulativeVarianceExplained": 0.2501872016,
    "Mask": "WM",
    "Method": "aCompCor",
    "Retained": true,
    "SingularValue": 114.1193676892,
    "VarianceExplained": 0.002545656
  },
  "w_comp_cor_82": {
    "CumulativeVarianceExplained": 0.2527274349,
    "Mask": "WM",
    "Method": "aCompCor",
    "Retained": true,
    "SingularValue": 113.9977532369,
    "VarianceExplained": 0.0025402332
  },
  "w_comp_cor_83": {
    "CumulativeVarianceExplained": 0.2552610468,
    "Mask": "WM",
    "Method": "aCompCor",
    "Retained": true,
    "SingularValue": 113.8490844035,
    "VarianceExplained": 0.0025336119
  },
  "w_comp_cor_84": {
    "CumulativeVarianceExplained": 0.2577916663,
    "Mask": "WM",
    "Method": "aCompCor",
    "Retained": true,
    "SingularValue": 113.7818310262,
    "VarianceExplained": 0.0025306195
  },
  "w_comp_cor_85": {
    "CumulativeVarianceExplained": 0.2603180414,
    "Mask": "WM",
    "Method": "aCompCor",
    "Retained": true,
    "SingularValue": 113.6863739524,
    "VarianceExplained": 0.0025263751
  },
  "w_comp_cor_86": {
    "CumulativeVarianceExplained": 0.2628390637,
    "Mask": "WM",
    "Method": "aCompCor",
    "Retained": true,
    "SingularValue": 113.5658708397,
    "VarianceExplained": 0.0025210223
  },
  "w_comp_cor_87": {
    "CumulativeVarianceExplained": 0.2653557289,
    "Mask": "WM",
    "Method": "aCompCor",
    "Retained": true,
    "SingularValue": 113.4676926819,
    "VarianceExplained": 0.0025166653
  },
  "w_comp_cor_88": {
    "CumulativeVarianceExplained": 0.2678663444,
    "Mask": "WM",
    "Method": "aCompCor",
    "Retained": true,
    "SingularValue": 113.3312281515,
    "VarianceExplained": 0.0025106155
  },
  "w_comp_cor_89": {
    "CumulativeVarianceExplained": 0.2703752152,
    "Mask": "WM",
    "Method": "aCompCor",
    "Retained": true,
    "SingularValue": 113.2918442213,
    "VarianceExplained": 0.0025088708
  },
  "w_comp_cor_90": {
    "CumulativeVarianceExplained": 0.2728774335,
    "Mask": "WM",
    "Method": "aCompCor",
    "Retained": true,
    "SingularValue": 113.1415419783,
    "VarianceExplained": 0.0025022183
  },
  "w_comp_cor_91": {
    "CumulativeVarianceExplained": 0.2753771294,
    "Mask": "WM",
    "Method": "aCompCor",
    "Retained": true,
    "SingularValue": 113.0844988502,
    "VarianceExplained": 0.0024996958
  },
  "w_comp_cor_92": {
    "CumulativeVarianceExplained": 0.2778736624,
    "Mask": "WM",
    "Method": "aCompCor",
    "Retained": true,
    "SingularValue": 113.0129348915,
    "VarianceExplained": 0.002496533
  },
  "w_comp_cor_93": {
    "CumulativeVarianceExplained": 0.2803662757,
    "Mask": "WM",
    "Method": "aCompCor",
    "Retained": true,
    "SingularValue": 112.9241818184,
    "VarianceExplained": 0.0024926133
  },
  "w_comp_cor_94": {
    "CumulativeVarianceExplained": 0.282855161,
    "Mask": "WM",
    "Method": "aCompCor",
    "Retained": true,
    "SingularValue": 112.8397022414,
    "VarianceExplained": 0.0024888852
  },
  "w_comp_cor_95": {
    "CumulativeVarianceExplained": 0.2853385555,
    "Mask": "WM",
    "Method": "aCompCor",
    "Retained": true,
    "SingularValue": 112.7151670647,
    "VarianceExplained": 0.0024833946
  },
  "w_comp_cor_96": {
    "CumulativeVarianceExplained": 0.2878144851,
    "Mask": "WM",
    "Method": "aCompCor",
    "Retained": true,
    "SingularValue": 112.5456306545,
    "VarianceExplained": 0.0024759296
  },
  "w_comp_cor_97": {
    "CumulativeVarianceExplained": 0.2902847998,
    "Mask": "WM",
    "Method": "aCompCor",
    "Retained": true,
    "SingularValue": 112.4179436983,
    "VarianceExplained": 0.0024703147
  },
  "w_comp_cor_98": {
    "CumulativeVarianceExplained": 0.2927501793,
    "Mask": "WM",
    "Method": "aCompCor",
    "Retained": true,
    "SingularValue": 112.3055929885,
    "VarianceExplained": 0.0024653795
  },
  "w_comp_cor_99": {
    "CumulativeVarianceExplained": 0.2952151807,
    "Mask": "WM",
    "Method": "aCompCor",
    "Retained": true,
    "SingularValue": 112.2969803731,
    "VarianceExplained": 0.0024650014
  },
  "white_matter": {
    "Method": "Mean"
  }
}